{
    "/js/app.js": "/js/app.js",
    "/css/app.css": "/css/app.css",
    "/js/app.e52c46294c82c5184b94.hot-update.js": "/js/app.e52c46294c82c5184b94.hot-update.js",
    "/js/app.147d72a576d792aaa9d4.hot-update.js": "/js/app.147d72a576d792aaa9d4.hot-update.js",
    "/js/app.17851f648b270aae7b40.hot-update.js": "/js/app.17851f648b270aae7b40.hot-update.js",
    "/js/app.3c2d1d172c41c407f9ef.hot-update.js": "/js/app.3c2d1d172c41c407f9ef.hot-update.js",
    "/js/app.5a98df5ab79738cd1bf1.hot-update.js": "/js/app.5a98df5ab79738cd1bf1.hot-update.js",
    "/js/app.07e2bbb1513f2ffe08e1.hot-update.js": "/js/app.07e2bbb1513f2ffe08e1.hot-update.js",
    "/js/app.bb629b67b4bba8185d4c.hot-update.js": "/js/app.bb629b67b4bba8185d4c.hot-update.js",
    "/js/app.6af3a644a481b08b2458.hot-update.js": "/js/app.6af3a644a481b08b2458.hot-update.js",
    "/js/app.58882c4da2340f124065.hot-update.js": "/js/app.58882c4da2340f124065.hot-update.js",
    "/js/app.e18485b566a07ef65817.hot-update.js": "/js/app.e18485b566a07ef65817.hot-update.js",
    "/js/app.9cb3d3075376b4761ba8.hot-update.js": "/js/app.9cb3d3075376b4761ba8.hot-update.js",
    "/js/app.13f7b8506c5a34fb11ff.hot-update.js": "/js/app.13f7b8506c5a34fb11ff.hot-update.js",
    "/js/app.ec7e9ddcc0bbf1aef6fa.hot-update.js": "/js/app.ec7e9ddcc0bbf1aef6fa.hot-update.js",
    "/js/app.39a9b1254624cfaf3e7a.hot-update.js": "/js/app.39a9b1254624cfaf3e7a.hot-update.js",
    "/js/app.3df091f1513cd3105019.hot-update.js": "/js/app.3df091f1513cd3105019.hot-update.js",
    "/js/app.e21aeb29e43dce35ba8a.hot-update.js": "/js/app.e21aeb29e43dce35ba8a.hot-update.js",
    "/js/app.12962ce0790856f5123a.hot-update.js": "/js/app.12962ce0790856f5123a.hot-update.js",
    "/js/app.0c7575e60da9be3c14b5.hot-update.js": "/js/app.0c7575e60da9be3c14b5.hot-update.js",
    "/js/app.b6e708f464ff99c97657.hot-update.js": "/js/app.b6e708f464ff99c97657.hot-update.js",
    "/js/app.967600c13eb07ed404ef.hot-update.js": "/js/app.967600c13eb07ed404ef.hot-update.js",
    "/js/app.03ad710ee0f6555fb80d.hot-update.js": "/js/app.03ad710ee0f6555fb80d.hot-update.js",
    "/js/app.1ba3e2fb32f7440dbe5f.hot-update.js": "/js/app.1ba3e2fb32f7440dbe5f.hot-update.js",
    "/js/app.cfb23f37376e7f4d01b8.hot-update.js": "/js/app.cfb23f37376e7f4d01b8.hot-update.js",
    "/js/app.860690970d6e76c1a741.hot-update.js": "/js/app.860690970d6e76c1a741.hot-update.js",
    "/js/app.c20a450289a85b120d75.hot-update.js": "/js/app.c20a450289a85b120d75.hot-update.js",
    "/js/app.4dfbfe63dac57dcf57c5.hot-update.js": "/js/app.4dfbfe63dac57dcf57c5.hot-update.js",
    "/js/app.c80c350ca07337298f5c.hot-update.js": "/js/app.c80c350ca07337298f5c.hot-update.js",
    "/js/app.c118782f1af14a5ba891.hot-update.js": "/js/app.c118782f1af14a5ba891.hot-update.js",
    "/js/app.65d4b39ffea6c681897b.hot-update.js": "/js/app.65d4b39ffea6c681897b.hot-update.js",
    "/js/app.8e6acfff691b946cf5e2.hot-update.js": "/js/app.8e6acfff691b946cf5e2.hot-update.js",
    "/js/app.3ef9e86206ab9cf16cd8.hot-update.js": "/js/app.3ef9e86206ab9cf16cd8.hot-update.js",
    "/js/app.b81b59bfc81e40e5408d.hot-update.js": "/js/app.b81b59bfc81e40e5408d.hot-update.js",
    "/js/app.15fbfd04208dea9a8e02.hot-update.js": "/js/app.15fbfd04208dea9a8e02.hot-update.js",
    "/js/app.0c353fc6159460efb557.hot-update.js": "/js/app.0c353fc6159460efb557.hot-update.js",
    "/js/app.016c6c4e8dcf318e9201.hot-update.js": "/js/app.016c6c4e8dcf318e9201.hot-update.js",
    "/js/app.6712fcd7042ed11b109c.hot-update.js": "/js/app.6712fcd7042ed11b109c.hot-update.js",
    "/js/app.b5505f6a60590df6ba1a.hot-update.js": "/js/app.b5505f6a60590df6ba1a.hot-update.js",
    "/js/app.a050147491c565d49e20.hot-update.js": "/js/app.a050147491c565d49e20.hot-update.js",
    "/js/app.71ecadeaceb262109f98.hot-update.js": "/js/app.71ecadeaceb262109f98.hot-update.js",
    "/js/app.a85d3fe6f72e5edb1dbd.hot-update.js": "/js/app.a85d3fe6f72e5edb1dbd.hot-update.js",
    "/js/app.b0fa96b59e6797ce86bc.hot-update.js": "/js/app.b0fa96b59e6797ce86bc.hot-update.js",
    "/js/app.ac1c889eed1b2f116217.hot-update.js": "/js/app.ac1c889eed1b2f116217.hot-update.js",
    "/js/app.60dcb3626caf463c6675.hot-update.js": "/js/app.60dcb3626caf463c6675.hot-update.js",
    "/js/app.2d06dc79600875e8d1c1.hot-update.js": "/js/app.2d06dc79600875e8d1c1.hot-update.js",
    "/js/app.756460347156e76df37c.hot-update.js": "/js/app.756460347156e76df37c.hot-update.js",
    "/js/app.e0da1004fc146234654c.hot-update.js": "/js/app.e0da1004fc146234654c.hot-update.js",
    "/js/app.f9376c3cc9ccb179f730.hot-update.js": "/js/app.f9376c3cc9ccb179f730.hot-update.js",
    "/js/app.70fbaddef0f98e1a714b.hot-update.js": "/js/app.70fbaddef0f98e1a714b.hot-update.js",
    "/js/app.7c18eb6ff978b0a7adbf.hot-update.js": "/js/app.7c18eb6ff978b0a7adbf.hot-update.js",
    "/js/app.d7b1d9914e495642afea.hot-update.js": "/js/app.d7b1d9914e495642afea.hot-update.js",
    "/js/app.5751252381467b5441ea.hot-update.js": "/js/app.5751252381467b5441ea.hot-update.js",
    "/js/app.6d5a856f56c5f51f860c.hot-update.js": "/js/app.6d5a856f56c5f51f860c.hot-update.js",
    "/js/app.1080784f4ba67beeb074.hot-update.js": "/js/app.1080784f4ba67beeb074.hot-update.js",
    "/js/app.ea3b7f87013861e47788.hot-update.js": "/js/app.ea3b7f87013861e47788.hot-update.js",
    "/js/app.d0c2c4c9e1c5610eb992.hot-update.js": "/js/app.d0c2c4c9e1c5610eb992.hot-update.js",
    "/js/app.310a289349dae7eb2eaf.hot-update.js": "/js/app.310a289349dae7eb2eaf.hot-update.js",
    "/js/app.05b842fdf6915d474cc4.hot-update.js": "/js/app.05b842fdf6915d474cc4.hot-update.js",
    "/js/app.0f1ed23d4c327e75054a.hot-update.js": "/js/app.0f1ed23d4c327e75054a.hot-update.js",
    "/js/app.93b2f41b2a745014e7ae.hot-update.js": "/js/app.93b2f41b2a745014e7ae.hot-update.js",
    "/js/app.bb37d14e58f383ef91b1.hot-update.js": "/js/app.bb37d14e58f383ef91b1.hot-update.js",
    "/js/app.2c88e9998be85f7291d4.hot-update.js": "/js/app.2c88e9998be85f7291d4.hot-update.js",
    "/js/app.c202b38eb27393da8368.hot-update.js": "/js/app.c202b38eb27393da8368.hot-update.js",
    "/js/app.f860e7f9c1066c99413b.hot-update.js": "/js/app.f860e7f9c1066c99413b.hot-update.js",
    "/js/app.75b1c1585cc7bf097fa0.hot-update.js": "/js/app.75b1c1585cc7bf097fa0.hot-update.js",
    "/js/app.c41d9085638b00e56a7f.hot-update.js": "/js/app.c41d9085638b00e56a7f.hot-update.js",
    "/js/app.15a1d2fb58a392bb41f7.hot-update.js": "/js/app.15a1d2fb58a392bb41f7.hot-update.js",
    "/js/app.6741f84bf18791faeafa.hot-update.js": "/js/app.6741f84bf18791faeafa.hot-update.js",
    "/js/app.6ffda89d101ffdee83a5.hot-update.js": "/js/app.6ffda89d101ffdee83a5.hot-update.js",
    "/js/app.9b143f344792e040e61f.hot-update.js": "/js/app.9b143f344792e040e61f.hot-update.js",
    "/js/app.7be26b6b5f9ab5b1937a.hot-update.js": "/js/app.7be26b6b5f9ab5b1937a.hot-update.js",
    "/js/app.1f7d0d5e9bcc0bc88be6.hot-update.js": "/js/app.1f7d0d5e9bcc0bc88be6.hot-update.js",
    "/js/app.dead92a1561e7cceda41.hot-update.js": "/js/app.dead92a1561e7cceda41.hot-update.js",
    "/js/app.326d4088dec5114f53d9.hot-update.js": "/js/app.326d4088dec5114f53d9.hot-update.js",
    "/js/app.1fa62283621c692eb0c4.hot-update.js": "/js/app.1fa62283621c692eb0c4.hot-update.js",
    "/js/app.ba7e854abea5eca135ec.hot-update.js": "/js/app.ba7e854abea5eca135ec.hot-update.js",
    "/js/app.730c8f28c09704bbfdd6.hot-update.js": "/js/app.730c8f28c09704bbfdd6.hot-update.js",
    "/js/app.4856f70cb7d72de6dabd.hot-update.js": "/js/app.4856f70cb7d72de6dabd.hot-update.js",
    "/js/app.2b95b2f9acaf6194e291.hot-update.js": "/js/app.2b95b2f9acaf6194e291.hot-update.js",
    "/js/app.8b101e6259f34f01f77d.hot-update.js": "/js/app.8b101e6259f34f01f77d.hot-update.js",
    "/js/app.85184f00f6dc5fd51539.hot-update.js": "/js/app.85184f00f6dc5fd51539.hot-update.js",
    "/js/app.9199a3601cc5d26f19a3.hot-update.js": "/js/app.9199a3601cc5d26f19a3.hot-update.js",
    "/js/app.6a65b6a4c9f92dc77b99.hot-update.js": "/js/app.6a65b6a4c9f92dc77b99.hot-update.js",
    "/js/app.c44cece349bdf85eef1d.hot-update.js": "/js/app.c44cece349bdf85eef1d.hot-update.js",
    "/js/app.79b0bea6e50748932ac8.hot-update.js": "/js/app.79b0bea6e50748932ac8.hot-update.js",
    "/js/app.543b154e03cabc1c0ff8.hot-update.js": "/js/app.543b154e03cabc1c0ff8.hot-update.js",
    "/js/app.aeb750fb1ebeb01f197d.hot-update.js": "/js/app.aeb750fb1ebeb01f197d.hot-update.js",
    "/js/app.053bae7f2f8e06f96e95.hot-update.js": "/js/app.053bae7f2f8e06f96e95.hot-update.js",
    "/js/app.2e81ebdeeca10ca17fa5.hot-update.js": "/js/app.2e81ebdeeca10ca17fa5.hot-update.js",
    "/js/app.87bf24d0423f721c9d80.hot-update.js": "/js/app.87bf24d0423f721c9d80.hot-update.js",
    "/js/app.e7a342f0a1f7b7200842.hot-update.js": "/js/app.e7a342f0a1f7b7200842.hot-update.js",
    "/js/app.c9f1d9c847ac16f519d0.hot-update.js": "/js/app.c9f1d9c847ac16f519d0.hot-update.js",
    "/js/app.00378a4bdbe3e02e1e4e.hot-update.js": "/js/app.00378a4bdbe3e02e1e4e.hot-update.js",
    "/js/app.cc17e17e5d6a2db20e00.hot-update.js": "/js/app.cc17e17e5d6a2db20e00.hot-update.js",
    "/js/app.2341b0a571cc9fea43f0.hot-update.js": "/js/app.2341b0a571cc9fea43f0.hot-update.js",
    "/js/app.b8192122cf833c3bd743.hot-update.js": "/js/app.b8192122cf833c3bd743.hot-update.js",
    "/js/app.e67db82459b60097f584.hot-update.js": "/js/app.e67db82459b60097f584.hot-update.js",
    "/js/app.bc89175699fa37fcc560.hot-update.js": "/js/app.bc89175699fa37fcc560.hot-update.js",
    "/js/app.7570af49b3b3ff5d3d9a.hot-update.js": "/js/app.7570af49b3b3ff5d3d9a.hot-update.js",
    "/js/app.db245a23abc7ecc73def.hot-update.js": "/js/app.db245a23abc7ecc73def.hot-update.js",
    "/js/app.c791e2dd1cd263b68855.hot-update.js": "/js/app.c791e2dd1cd263b68855.hot-update.js",
    "/js/app.dd486831255b82ee857f.hot-update.js": "/js/app.dd486831255b82ee857f.hot-update.js",
    "/js/app.8682317d10f2c40d7154.hot-update.js": "/js/app.8682317d10f2c40d7154.hot-update.js",
    "/js/app.11f5d9863fff35bd79f8.hot-update.js": "/js/app.11f5d9863fff35bd79f8.hot-update.js",
    "/js/app.04ed43b95c8e716fec02.hot-update.js": "/js/app.04ed43b95c8e716fec02.hot-update.js",
    "/js/app.9c8e68b2612b54e6b9cf.hot-update.js": "/js/app.9c8e68b2612b54e6b9cf.hot-update.js",
    "/js/app.b2e2828ceb1f4c7306b6.hot-update.js": "/js/app.b2e2828ceb1f4c7306b6.hot-update.js",
    "/js/app.f813811e1fdde882783d.hot-update.js": "/js/app.f813811e1fdde882783d.hot-update.js",
    "/js/app.afeb1d6997c2d17bb8c1.hot-update.js": "/js/app.afeb1d6997c2d17bb8c1.hot-update.js",
    "/js/app.2a0f7986433f837a58fa.hot-update.js": "/js/app.2a0f7986433f837a58fa.hot-update.js",
    "/js/app.24cef2fc14308b84e4ca.hot-update.js": "/js/app.24cef2fc14308b84e4ca.hot-update.js",
    "/js/app.5bb91b6b75a39f321829.hot-update.js": "/js/app.5bb91b6b75a39f321829.hot-update.js",
    "/js/app.ff81374850a69794ec36.hot-update.js": "/js/app.ff81374850a69794ec36.hot-update.js",
    "/js/app.9d060a5c66ec5df1e04d.hot-update.js": "/js/app.9d060a5c66ec5df1e04d.hot-update.js",
    "/js/app.3bd7d2697893f20995b5.hot-update.js": "/js/app.3bd7d2697893f20995b5.hot-update.js",
    "/js/app.c491bded276df79433ea.hot-update.js": "/js/app.c491bded276df79433ea.hot-update.js",
    "/js/app.a533622979cc7d81aa8b.hot-update.js": "/js/app.a533622979cc7d81aa8b.hot-update.js",
    "/js/app.9d91688d5192cc4e1aa1.hot-update.js": "/js/app.9d91688d5192cc4e1aa1.hot-update.js",
    "/js/app.c5cb176e351eb106ea15.hot-update.js": "/js/app.c5cb176e351eb106ea15.hot-update.js",
    "/js/app.e6e29511488ff3f3d442.hot-update.js": "/js/app.e6e29511488ff3f3d442.hot-update.js",
    "/js/app.212b931901022ac6df17.hot-update.js": "/js/app.212b931901022ac6df17.hot-update.js",
    "/js/app.5532b85904243a99c840.hot-update.js": "/js/app.5532b85904243a99c840.hot-update.js",
    "/js/app.4c9ef31e2166936d9004.hot-update.js": "/js/app.4c9ef31e2166936d9004.hot-update.js",
    "/js/app.b2ad8a4f085de3dde2fb.hot-update.js": "/js/app.b2ad8a4f085de3dde2fb.hot-update.js",
    "/js/app.c301fb0b5bfa08a79e18.hot-update.js": "/js/app.c301fb0b5bfa08a79e18.hot-update.js",
    "/js/app.5dbf9093c42af01ee020.hot-update.js": "/js/app.5dbf9093c42af01ee020.hot-update.js",
    "/js/app.6f1cb5508f153ec6c2d3.hot-update.js": "/js/app.6f1cb5508f153ec6c2d3.hot-update.js",
    "/js/app.93829fb2202b59d2ed00.hot-update.js": "/js/app.93829fb2202b59d2ed00.hot-update.js",
    "/js/app.eb67ed5ed308f8b23c6f.hot-update.js": "/js/app.eb67ed5ed308f8b23c6f.hot-update.js",
    "/js/app.620b6480c26469694651.hot-update.js": "/js/app.620b6480c26469694651.hot-update.js",
    "/js/app.fd397e56af19aee72876.hot-update.js": "/js/app.fd397e56af19aee72876.hot-update.js",
    "/js/app.611b0b3efeef4fef01da.hot-update.js": "/js/app.611b0b3efeef4fef01da.hot-update.js",
    "/js/app.f8fd87c52a6e875559fd.hot-update.js": "/js/app.f8fd87c52a6e875559fd.hot-update.js",
    "/js/app.b7c9058b7d1af27055e2.hot-update.js": "/js/app.b7c9058b7d1af27055e2.hot-update.js",
    "/js/app.559073152f5a2d545079.hot-update.js": "/js/app.559073152f5a2d545079.hot-update.js",
    "/js/app.ddc63901f321959cae6a.hot-update.js": "/js/app.ddc63901f321959cae6a.hot-update.js",
    "/js/app.081afd94bbbde33cacf2.hot-update.js": "/js/app.081afd94bbbde33cacf2.hot-update.js",
    "/js/app.7ac7d09fb14ed830729a.hot-update.js": "/js/app.7ac7d09fb14ed830729a.hot-update.js",
    "/js/app.74d99b2b5402034312d8.hot-update.js": "/js/app.74d99b2b5402034312d8.hot-update.js",
    "/js/app.b97bde9bb137e2791659.hot-update.js": "/js/app.b97bde9bb137e2791659.hot-update.js",
    "/js/app.9e50e65b006fee7f7f83.hot-update.js": "/js/app.9e50e65b006fee7f7f83.hot-update.js",
    "/js/app.1d92b8410f39652ad0fc.hot-update.js": "/js/app.1d92b8410f39652ad0fc.hot-update.js",
    "/js/app.565b3e069280cd81979e.hot-update.js": "/js/app.565b3e069280cd81979e.hot-update.js",
    "/js/app.248af75d13e0e7b22b5f.hot-update.js": "/js/app.248af75d13e0e7b22b5f.hot-update.js",
    "/js/app.f48bad71535e0a13c3fc.hot-update.js": "/js/app.f48bad71535e0a13c3fc.hot-update.js",
    "/js/app.418157cd3c91cd5ad1ce.hot-update.js": "/js/app.418157cd3c91cd5ad1ce.hot-update.js",
    "/js/app.542e55057cc074a8669a.hot-update.js": "/js/app.542e55057cc074a8669a.hot-update.js",
    "/js/app.6494ad925ae6d2bf28c1.hot-update.js": "/js/app.6494ad925ae6d2bf28c1.hot-update.js",
    "/js/app.4e06b450193b00bffac7.hot-update.js": "/js/app.4e06b450193b00bffac7.hot-update.js",
    "/js/app.8b44190456e6121a9e14.hot-update.js": "/js/app.8b44190456e6121a9e14.hot-update.js",
    "/js/app.94a2ad1d21c17e969eae.hot-update.js": "/js/app.94a2ad1d21c17e969eae.hot-update.js",
    "/js/app.e931c98dd185db613e8c.hot-update.js": "/js/app.e931c98dd185db613e8c.hot-update.js",
    "/js/app.777cebbf18179fd78a85.hot-update.js": "/js/app.777cebbf18179fd78a85.hot-update.js",
    "/js/app.dfcae2b55ca0abb8df9a.hot-update.js": "/js/app.dfcae2b55ca0abb8df9a.hot-update.js",
    "/js/app.715fcec2fd2ef71b1050.hot-update.js": "/js/app.715fcec2fd2ef71b1050.hot-update.js",
    "/js/app.7d800e03552bb37e5c3d.hot-update.js": "/js/app.7d800e03552bb37e5c3d.hot-update.js",
    "/js/app.2adffe89c203f7da0ebd.hot-update.js": "/js/app.2adffe89c203f7da0ebd.hot-update.js",
    "/js/app.d8f316f01c2bf3631c2b.hot-update.js": "/js/app.d8f316f01c2bf3631c2b.hot-update.js",
    "/js/app.9fefa6e8253cdde62a75.hot-update.js": "/js/app.9fefa6e8253cdde62a75.hot-update.js",
    "/js/app.d1a49852e1e21e733699.hot-update.js": "/js/app.d1a49852e1e21e733699.hot-update.js",
    "/js/app.8320c68b0594b4862ebf.hot-update.js": "/js/app.8320c68b0594b4862ebf.hot-update.js",
    "/js/app.daf74aef141e40398350.hot-update.js": "/js/app.daf74aef141e40398350.hot-update.js",
    "/js/app.4c73cb0073b548054123.hot-update.js": "/js/app.4c73cb0073b548054123.hot-update.js",
    "/js/app.ba348fc778b1bdb1f1e3.hot-update.js": "/js/app.ba348fc778b1bdb1f1e3.hot-update.js",
    "/js/app.e2a8db0ebd4bf677448c.hot-update.js": "/js/app.e2a8db0ebd4bf677448c.hot-update.js",
    "/js/app.77d7f53a52c5ada6d637.hot-update.js": "/js/app.77d7f53a52c5ada6d637.hot-update.js",
    "/js/app.c46bedd7b4f95f82d482.hot-update.js": "/js/app.c46bedd7b4f95f82d482.hot-update.js",
    "/js/app.e6649fbcebc10d9dee4c.hot-update.js": "/js/app.e6649fbcebc10d9dee4c.hot-update.js",
    "/js/app.81eb9c0a3db07bf7a7ee.hot-update.js": "/js/app.81eb9c0a3db07bf7a7ee.hot-update.js",
    "/js/app.62569521635d2294c876.hot-update.js": "/js/app.62569521635d2294c876.hot-update.js",
    "/js/app.297154eb6c484979a3d0.hot-update.js": "/js/app.297154eb6c484979a3d0.hot-update.js",
    "/js/app.3558ef53ea3df28d3ea2.hot-update.js": "/js/app.3558ef53ea3df28d3ea2.hot-update.js",
    "/js/app.f8438f46dca2be237df4.hot-update.js": "/js/app.f8438f46dca2be237df4.hot-update.js",
    "/js/app.5496c169ddb69810e490.hot-update.js": "/js/app.5496c169ddb69810e490.hot-update.js",
    "/js/app.6675cf3dcb3bf57a1aba.hot-update.js": "/js/app.6675cf3dcb3bf57a1aba.hot-update.js",
    "/js/app.b2d6977d1e864c5e8a0e.hot-update.js": "/js/app.b2d6977d1e864c5e8a0e.hot-update.js",
    "/js/app.15e05d39c12c84d340ce.hot-update.js": "/js/app.15e05d39c12c84d340ce.hot-update.js",
    "/js/app.8d71b3a323b883dc0e9c.hot-update.js": "/js/app.8d71b3a323b883dc0e9c.hot-update.js",
    "/js/app.64975f5a99f00341819d.hot-update.js": "/js/app.64975f5a99f00341819d.hot-update.js",
    "/js/app.470bdc398e10c99e3e70.hot-update.js": "/js/app.470bdc398e10c99e3e70.hot-update.js",
    "/js/app.ea03bf1f808fede20492.hot-update.js": "/js/app.ea03bf1f808fede20492.hot-update.js",
    "/js/app.ffd76fc86a8aa01d42ca.hot-update.js": "/js/app.ffd76fc86a8aa01d42ca.hot-update.js",
    "/js/app.5f3503a3f2c855ec6c4a.hot-update.js": "/js/app.5f3503a3f2c855ec6c4a.hot-update.js",
    "/js/app.b51df141fdb6149e464d.hot-update.js": "/js/app.b51df141fdb6149e464d.hot-update.js",
    "/js/app.1e17336767451428712c.hot-update.js": "/js/app.1e17336767451428712c.hot-update.js",
    "/js/app.92a7574267d3de9fb0c9.hot-update.js": "/js/app.92a7574267d3de9fb0c9.hot-update.js",
    "/js/app.43c08006ad05a6ddd949.hot-update.js": "/js/app.43c08006ad05a6ddd949.hot-update.js",
    "/js/app.36584b7ce7887de69085.hot-update.js": "/js/app.36584b7ce7887de69085.hot-update.js",
    "/js/app.7e812d89a527f3920230.hot-update.js": "/js/app.7e812d89a527f3920230.hot-update.js",
    "/js/app.a38159639d0179ea38be.hot-update.js": "/js/app.a38159639d0179ea38be.hot-update.js",
    "/js/app.1f1d811befab5b3bd81d.hot-update.js": "/js/app.1f1d811befab5b3bd81d.hot-update.js",
    "/js/app.df2f3f487f51365a0c47.hot-update.js": "/js/app.df2f3f487f51365a0c47.hot-update.js",
    "/js/app.9d4afe0f327324351b84.hot-update.js": "/js/app.9d4afe0f327324351b84.hot-update.js",
    "/js/app.fb1b715c13cdec69ffb8.hot-update.js": "/js/app.fb1b715c13cdec69ffb8.hot-update.js",
    "/js/app.e2802c429288d68326ab.hot-update.js": "/js/app.e2802c429288d68326ab.hot-update.js",
    "/js/app.1671378ae58003caac72.hot-update.js": "/js/app.1671378ae58003caac72.hot-update.js",
    "/js/app.73770f7cdb39f94e0a0b.hot-update.js": "/js/app.73770f7cdb39f94e0a0b.hot-update.js",
    "/js/app.21567087ad6c09b0ffe2.hot-update.js": "/js/app.21567087ad6c09b0ffe2.hot-update.js",
    "/js/app.8a9b8c7f28cf4c9d3420.hot-update.js": "/js/app.8a9b8c7f28cf4c9d3420.hot-update.js",
    "/js/app.5b5eec9497c69a50e979.hot-update.js": "/js/app.5b5eec9497c69a50e979.hot-update.js",
    "/js/app.de938f05f64f331a9ea1.hot-update.js": "/js/app.de938f05f64f331a9ea1.hot-update.js",
    "/js/app.a002e2f27c21e4f6eed4.hot-update.js": "/js/app.a002e2f27c21e4f6eed4.hot-update.js",
    "/js/app.031773656975249ab588.hot-update.js": "/js/app.031773656975249ab588.hot-update.js",
    "/js/app.5de5268e157de68c9758.hot-update.js": "/js/app.5de5268e157de68c9758.hot-update.js",
    "/js/app.01ce0aa59201437e0117.hot-update.js": "/js/app.01ce0aa59201437e0117.hot-update.js",
    "/js/app.d7ee6b1cf33f7093751c.hot-update.js": "/js/app.d7ee6b1cf33f7093751c.hot-update.js",
    "/js/app.4f15480f8aa68b07db14.hot-update.js": "/js/app.4f15480f8aa68b07db14.hot-update.js",
    "/js/app.5b9c2c8c69fda55b0b92.hot-update.js": "/js/app.5b9c2c8c69fda55b0b92.hot-update.js",
    "/js/app.d39f8f7f7ab6480bbfe0.hot-update.js": "/js/app.d39f8f7f7ab6480bbfe0.hot-update.js",
    "/js/app.7a116b054bd74f0e9d9c.hot-update.js": "/js/app.7a116b054bd74f0e9d9c.hot-update.js",
    "/js/app.36803daa1e27afc2c987.hot-update.js": "/js/app.36803daa1e27afc2c987.hot-update.js",
    "/js/app.e5261080e5d074fe1a0f.hot-update.js": "/js/app.e5261080e5d074fe1a0f.hot-update.js",
    "/js/app.7ece6ac2e8e59a00a9ad.hot-update.js": "/js/app.7ece6ac2e8e59a00a9ad.hot-update.js",
    "/js/app.ef4f1b5c51b2136c2143.hot-update.js": "/js/app.ef4f1b5c51b2136c2143.hot-update.js",
    "/js/app.a1e2dc7b5e438c11ebaf.hot-update.js": "/js/app.a1e2dc7b5e438c11ebaf.hot-update.js",
    "/js/app.b8a39c056ea4c1970a8a.hot-update.js": "/js/app.b8a39c056ea4c1970a8a.hot-update.js",
    "/js/app.e1af9b7a0e0babb824f8.hot-update.js": "/js/app.e1af9b7a0e0babb824f8.hot-update.js",
    "/js/app.b57a523bfcb748820260.hot-update.js": "/js/app.b57a523bfcb748820260.hot-update.js",
    "/js/app.df38bbf4dbbe271592c5.hot-update.js": "/js/app.df38bbf4dbbe271592c5.hot-update.js",
    "/js/app.cc6db028e3d9bdaf48c5.hot-update.js": "/js/app.cc6db028e3d9bdaf48c5.hot-update.js",
    "/js/app.9c9f722feab70dfa3da0.hot-update.js": "/js/app.9c9f722feab70dfa3da0.hot-update.js",
    "/js/app.1639269ae985d44ad5c4.hot-update.js": "/js/app.1639269ae985d44ad5c4.hot-update.js",
    "/js/app.1fba58fd62a554acff55.hot-update.js": "/js/app.1fba58fd62a554acff55.hot-update.js",
    "/js/app.fd255ed320caab806dac.hot-update.js": "/js/app.fd255ed320caab806dac.hot-update.js",
    "/js/app.79f8a86887764f6be4be.hot-update.js": "/js/app.79f8a86887764f6be4be.hot-update.js",
    "/js/app.8d11da0a87a00252188b.hot-update.js": "/js/app.8d11da0a87a00252188b.hot-update.js",
    "/js/app.6bcd3460bcd19fafe54c.hot-update.js": "/js/app.6bcd3460bcd19fafe54c.hot-update.js",
    "/js/app.8e1869ad7a4224faf1dd.hot-update.js": "/js/app.8e1869ad7a4224faf1dd.hot-update.js",
    "/js/app.f9fc1aa063cb029b4ce6.hot-update.js": "/js/app.f9fc1aa063cb029b4ce6.hot-update.js",
    "/js/app.ac13378c2b3ce2d93168.hot-update.js": "/js/app.ac13378c2b3ce2d93168.hot-update.js",
    "/js/app.99957c544fb2f666c2de.hot-update.js": "/js/app.99957c544fb2f666c2de.hot-update.js",
    "/js/app.75700bb89a70820d8197.hot-update.js": "/js/app.75700bb89a70820d8197.hot-update.js",
    "/js/app.ed1d93c76ec58d2ff2f7.hot-update.js": "/js/app.ed1d93c76ec58d2ff2f7.hot-update.js",
    "/js/app.30a240955995f3839448.hot-update.js": "/js/app.30a240955995f3839448.hot-update.js",
    "/js/app.795cd3d3e394f46dfe02.hot-update.js": "/js/app.795cd3d3e394f46dfe02.hot-update.js",
    "/js/app.c64555f117dd55cde867.hot-update.js": "/js/app.c64555f117dd55cde867.hot-update.js",
    "/js/app.6f7f0d855df492f1f7d0.hot-update.js": "/js/app.6f7f0d855df492f1f7d0.hot-update.js",
    "/js/app.0ad95599b959ae783d5b.hot-update.js": "/js/app.0ad95599b959ae783d5b.hot-update.js",
    "/js/app.57cc505954ee1434efe6.hot-update.js": "/js/app.57cc505954ee1434efe6.hot-update.js",
    "/js/app.02268ab0b7d0f51b22e3.hot-update.js": "/js/app.02268ab0b7d0f51b22e3.hot-update.js",
    "/js/app.97d8c7e4c329ae005a02.hot-update.js": "/js/app.97d8c7e4c329ae005a02.hot-update.js",
    "/js/app.25713e2f3b4fb6dc0bb3.hot-update.js": "/js/app.25713e2f3b4fb6dc0bb3.hot-update.js",
    "/js/app.3c913f1594ae0436f08e.hot-update.js": "/js/app.3c913f1594ae0436f08e.hot-update.js",
    "/js/app.9e3a70da67882fadff19.hot-update.js": "/js/app.9e3a70da67882fadff19.hot-update.js",
    "/js/app.03fdd1b0b544771d6a34.hot-update.js": "/js/app.03fdd1b0b544771d6a34.hot-update.js",
    "/js/app.476df9ad07046fe0f633.hot-update.js": "/js/app.476df9ad07046fe0f633.hot-update.js",
    "/js/app.9d589d9ee4cbc18fb11b.hot-update.js": "/js/app.9d589d9ee4cbc18fb11b.hot-update.js",
    "/js/app.7a332ce10d96685d3b65.hot-update.js": "/js/app.7a332ce10d96685d3b65.hot-update.js",
    "/js/app.394fa6d84ef8b912d493.hot-update.js": "/js/app.394fa6d84ef8b912d493.hot-update.js",
    "/js/app.b7630783ef3c1f02abae.hot-update.js": "/js/app.b7630783ef3c1f02abae.hot-update.js",
    "/js/app.918a515119f04c02cb7d.hot-update.js": "/js/app.918a515119f04c02cb7d.hot-update.js",
    "/js/app.fc83f2a8842aa68bbbf6.hot-update.js": "/js/app.fc83f2a8842aa68bbbf6.hot-update.js",
    "/js/app.da3bf59f50ceeed037dc.hot-update.js": "/js/app.da3bf59f50ceeed037dc.hot-update.js",
    "/js/app.ddd9a94f8451fd258272.hot-update.js": "/js/app.ddd9a94f8451fd258272.hot-update.js",
    "/js/app.b621c957a1ad9bc796a9.hot-update.js": "/js/app.b621c957a1ad9bc796a9.hot-update.js",
    "/js/app.8499872c3dcf1710ee6a.hot-update.js": "/js/app.8499872c3dcf1710ee6a.hot-update.js",
    "/js/app.89c633732229b0c9b3ac.hot-update.js": "/js/app.89c633732229b0c9b3ac.hot-update.js",
    "/js/app.5f60c3f89fa6d933a21f.hot-update.js": "/js/app.5f60c3f89fa6d933a21f.hot-update.js",
    "/js/app.010246c438c01b4739d3.hot-update.js": "/js/app.010246c438c01b4739d3.hot-update.js",
    "/js/app.ad6e2a9c4dc43e5c9e1d.hot-update.js": "/js/app.ad6e2a9c4dc43e5c9e1d.hot-update.js",
    "/js/app.21d74381b3a35006a2f1.hot-update.js": "/js/app.21d74381b3a35006a2f1.hot-update.js",
    "/js/app.3d07a9fcfa3ef47b72b9.hot-update.js": "/js/app.3d07a9fcfa3ef47b72b9.hot-update.js",
    "/js/app.0ec1249680dcf7710197.hot-update.js": "/js/app.0ec1249680dcf7710197.hot-update.js",
    "/js/app.5234ce8046f1033fb403.hot-update.js": "/js/app.5234ce8046f1033fb403.hot-update.js",
    "/js/app.cf07eba93e7ce9612d72.hot-update.js": "/js/app.cf07eba93e7ce9612d72.hot-update.js",
    "/js/app.c754bac394fe973db886.hot-update.js": "/js/app.c754bac394fe973db886.hot-update.js",
    "/js/app.34eac7d1251d81c2e730.hot-update.js": "/js/app.34eac7d1251d81c2e730.hot-update.js",
    "/js/app.09a33d737ca6747e2a3f.hot-update.js": "/js/app.09a33d737ca6747e2a3f.hot-update.js",
    "/js/app.6d66dda01eebfec6258a.hot-update.js": "/js/app.6d66dda01eebfec6258a.hot-update.js",
    "/js/app.5f1522d6293d8e5a82cb.hot-update.js": "/js/app.5f1522d6293d8e5a82cb.hot-update.js",
    "/js/app.6925932b1f5a73b741dc.hot-update.js": "/js/app.6925932b1f5a73b741dc.hot-update.js",
    "/js/app.a31cb07460581d645665.hot-update.js": "/js/app.a31cb07460581d645665.hot-update.js",
    "/js/app.dd606cff880b2e410c7e.hot-update.js": "/js/app.dd606cff880b2e410c7e.hot-update.js",
    "/js/app.e0aacab1be86eee10012.hot-update.js": "/js/app.e0aacab1be86eee10012.hot-update.js",
    "/js/app.926f27dc6eaacc5b968f.hot-update.js": "/js/app.926f27dc6eaacc5b968f.hot-update.js",
    "/js/app.0aee35a1d948ad92207b.hot-update.js": "/js/app.0aee35a1d948ad92207b.hot-update.js",
    "/js/app.381af413efd1a5e1a5d8.hot-update.js": "/js/app.381af413efd1a5e1a5d8.hot-update.js",
    "/js/app.0a08342339ef0b8c2821.hot-update.js": "/js/app.0a08342339ef0b8c2821.hot-update.js",
    "/js/app.6984fb77b9f80eb7ac95.hot-update.js": "/js/app.6984fb77b9f80eb7ac95.hot-update.js",
    "/js/app.bfb595f1708f12f660bb.hot-update.js": "/js/app.bfb595f1708f12f660bb.hot-update.js",
    "/js/app.0b194bfb704a4a3e6d72.hot-update.js": "/js/app.0b194bfb704a4a3e6d72.hot-update.js",
    "/js/app.ebd0d80f9b7c2ee331ca.hot-update.js": "/js/app.ebd0d80f9b7c2ee331ca.hot-update.js",
    "/js/app.ad86155c654860c43630.hot-update.js": "/js/app.ad86155c654860c43630.hot-update.js",
    "/js/app.5770bf64028ce6c22ace.hot-update.js": "/js/app.5770bf64028ce6c22ace.hot-update.js",
    "/js/app.a12a50d6ea6ba0456b7d.hot-update.js": "/js/app.a12a50d6ea6ba0456b7d.hot-update.js",
    "/js/app.1fa695535b1dad92974e.hot-update.js": "/js/app.1fa695535b1dad92974e.hot-update.js",
    "/js/app.a52cea0201173dce2f6c.hot-update.js": "/js/app.a52cea0201173dce2f6c.hot-update.js",
    "/js/app.2d0ab2d7b03a2b46f86d.hot-update.js": "/js/app.2d0ab2d7b03a2b46f86d.hot-update.js",
    "/js/app.94fca4f80df1481421f0.hot-update.js": "/js/app.94fca4f80df1481421f0.hot-update.js",
    "/js/app.be2a4c2ee1fcdf74d92b.hot-update.js": "/js/app.be2a4c2ee1fcdf74d92b.hot-update.js",
    "/js/app.a065c8844bb3a4f9086c.hot-update.js": "/js/app.a065c8844bb3a4f9086c.hot-update.js",
    "/js/app.0f9c5b7ca39190911465.hot-update.js": "/js/app.0f9c5b7ca39190911465.hot-update.js",
    "/js/app.76c607a569b46a1fd064.hot-update.js": "/js/app.76c607a569b46a1fd064.hot-update.js",
    "/js/app.52664c49b70a0acc66c1.hot-update.js": "/js/app.52664c49b70a0acc66c1.hot-update.js",
    "/js/app.7c5389d46b2fadac038f.hot-update.js": "/js/app.7c5389d46b2fadac038f.hot-update.js",
    "/js/app.b3484ff98e8d7b9bd743.hot-update.js": "/js/app.b3484ff98e8d7b9bd743.hot-update.js",
    "/js/app.4062663129fab3462074.hot-update.js": "/js/app.4062663129fab3462074.hot-update.js",
    "/js/app.5f8e18364c2a174cdfbb.hot-update.js": "/js/app.5f8e18364c2a174cdfbb.hot-update.js",
    "/js/app.ec175e476805d1052b85.hot-update.js": "/js/app.ec175e476805d1052b85.hot-update.js",
    "/js/app.5f5d6dd0f283b759ab03.hot-update.js": "/js/app.5f5d6dd0f283b759ab03.hot-update.js",
    "/js/app.e89b42d015d3eac1cfcc.hot-update.js": "/js/app.e89b42d015d3eac1cfcc.hot-update.js",
    "/js/app.4a10ec38a10574cc03dd.hot-update.js": "/js/app.4a10ec38a10574cc03dd.hot-update.js",
    "/js/app.35756f0b6fdc56999e3f.hot-update.js": "/js/app.35756f0b6fdc56999e3f.hot-update.js",
    "/js/app.3966edfa698b8e91a016.hot-update.js": "/js/app.3966edfa698b8e91a016.hot-update.js",
    "/js/app.42d2f02ef9de70e97c5e.hot-update.js": "/js/app.42d2f02ef9de70e97c5e.hot-update.js",
    "/js/app.2310bd5dae0e74edeb43.hot-update.js": "/js/app.2310bd5dae0e74edeb43.hot-update.js",
    "/js/app.ff42076d5e8e30604ca8.hot-update.js": "/js/app.ff42076d5e8e30604ca8.hot-update.js",
    "/js/app.70e78d25187efb3eec03.hot-update.js": "/js/app.70e78d25187efb3eec03.hot-update.js",
    "/js/app.6c065ae2209345cc01ac.hot-update.js": "/js/app.6c065ae2209345cc01ac.hot-update.js",
    "/js/app.e75039a2f3ab77616a3f.hot-update.js": "/js/app.e75039a2f3ab77616a3f.hot-update.js",
    "/js/app.b6176d7ce6c468a4f186.hot-update.js": "/js/app.b6176d7ce6c468a4f186.hot-update.js",
    "/js/app.2733e8ad4866c1cc4685.hot-update.js": "/js/app.2733e8ad4866c1cc4685.hot-update.js",
    "/js/app.7cbabe32e6d4fd05575f.hot-update.js": "/js/app.7cbabe32e6d4fd05575f.hot-update.js",
    "/js/app.44d7edeb8b622a5e3d14.hot-update.js": "/js/app.44d7edeb8b622a5e3d14.hot-update.js",
    "/js/app.1d917ee1387a8af6914c.hot-update.js": "/js/app.1d917ee1387a8af6914c.hot-update.js",
    "/js/app.b4739876aeffa06a55e5.hot-update.js": "/js/app.b4739876aeffa06a55e5.hot-update.js",
    "/js/app.c2883bf2c484f918fcbc.hot-update.js": "/js/app.c2883bf2c484f918fcbc.hot-update.js",
    "/js/app.f1b37f6d36b734095cd6.hot-update.js": "/js/app.f1b37f6d36b734095cd6.hot-update.js",
    "/js/app.76ea9cecb12fe3ceb1c7.hot-update.js": "/js/app.76ea9cecb12fe3ceb1c7.hot-update.js",
    "/js/app.5c3d813ece857ab4cd79.hot-update.js": "/js/app.5c3d813ece857ab4cd79.hot-update.js",
    "/js/app.5aa788861d34c601c6cd.hot-update.js": "/js/app.5aa788861d34c601c6cd.hot-update.js",
    "/js/app.749c0c0b5f00aab02bbf.hot-update.js": "/js/app.749c0c0b5f00aab02bbf.hot-update.js",
    "/js/app.164cefb58c73ba1ccc17.hot-update.js": "/js/app.164cefb58c73ba1ccc17.hot-update.js",
    "/js/app.2bedba2c44a82bf9546d.hot-update.js": "/js/app.2bedba2c44a82bf9546d.hot-update.js",
    "/js/app.0fe6174eae44d25455cf.hot-update.js": "/js/app.0fe6174eae44d25455cf.hot-update.js",
    "/js/app.4bcdc13c2c8d4527f314.hot-update.js": "/js/app.4bcdc13c2c8d4527f314.hot-update.js",
    "/js/app.63ed3f9751d2d4e6b25b.hot-update.js": "/js/app.63ed3f9751d2d4e6b25b.hot-update.js",
    "/js/app.895e28769f7785b1e418.hot-update.js": "/js/app.895e28769f7785b1e418.hot-update.js",
    "/js/app.87c0e883964bec8c1a57.hot-update.js": "/js/app.87c0e883964bec8c1a57.hot-update.js",
    "/js/app.adc99063c5eaa2f3774b.hot-update.js": "/js/app.adc99063c5eaa2f3774b.hot-update.js",
    "/js/app.e6ed17195411123c3cfa.hot-update.js": "/js/app.e6ed17195411123c3cfa.hot-update.js",
    "/js/app.f47abc124828c51b49f9.hot-update.js": "/js/app.f47abc124828c51b49f9.hot-update.js",
    "/js/app.2ac164694145231817fc.hot-update.js": "/js/app.2ac164694145231817fc.hot-update.js",
    "/js/app.efb0e7c9376569129f44.hot-update.js": "/js/app.efb0e7c9376569129f44.hot-update.js",
    "/js/app.d1c8a227a2090abccf8c.hot-update.js": "/js/app.d1c8a227a2090abccf8c.hot-update.js",
    "/js/app.f0f52faed4bfdb2228f1.hot-update.js": "/js/app.f0f52faed4bfdb2228f1.hot-update.js",
    "/js/app.889bd1e0b7bf2d95c14f.hot-update.js": "/js/app.889bd1e0b7bf2d95c14f.hot-update.js",
    "/js/app.8e218411a3805a61b2e1.hot-update.js": "/js/app.8e218411a3805a61b2e1.hot-update.js",
    "/js/app.d755e40ffd148ecee092.hot-update.js": "/js/app.d755e40ffd148ecee092.hot-update.js",
    "/js/app.447a49388ee0b7dada7d.hot-update.js": "/js/app.447a49388ee0b7dada7d.hot-update.js",
    "/js/app.03f13e4254e8430e1df2.hot-update.js": "/js/app.03f13e4254e8430e1df2.hot-update.js",
    "/js/app.444a71571fb188f502a6.hot-update.js": "/js/app.444a71571fb188f502a6.hot-update.js",
    "/js/app.3e5ef9aec98fe23cbcda.hot-update.js": "/js/app.3e5ef9aec98fe23cbcda.hot-update.js",
    "/js/app.5d564f797344cb6e2be8.hot-update.js": "/js/app.5d564f797344cb6e2be8.hot-update.js",
    "/js/app.8a76d5c3fcc04a3567c9.hot-update.js": "/js/app.8a76d5c3fcc04a3567c9.hot-update.js",
    "/js/app.b654080a684d1b79bc10.hot-update.js": "/js/app.b654080a684d1b79bc10.hot-update.js",
    "/js/app.2017d1b5e74228c3a122.hot-update.js": "/js/app.2017d1b5e74228c3a122.hot-update.js",
    "/js/app.24e024c1ccaceed61ed0.hot-update.js": "/js/app.24e024c1ccaceed61ed0.hot-update.js",
    "/js/app.f504298c0954c9db36ec.hot-update.js": "/js/app.f504298c0954c9db36ec.hot-update.js",
    "/js/app.a0019a96a8a6b5f9fc55.hot-update.js": "/js/app.a0019a96a8a6b5f9fc55.hot-update.js",
    "/js/app.4de12027315a25d78952.hot-update.js": "/js/app.4de12027315a25d78952.hot-update.js",
    "/js/app.efce6b4f7298a6027d4d.hot-update.js": "/js/app.efce6b4f7298a6027d4d.hot-update.js",
    "/js/app.7fe690270601512cedc7.hot-update.js": "/js/app.7fe690270601512cedc7.hot-update.js",
    "/js/app.92cbf4eae6d5e4d67dbc.hot-update.js": "/js/app.92cbf4eae6d5e4d67dbc.hot-update.js",
    "/js/app.cd97493f274a56e65a3c.hot-update.js": "/js/app.cd97493f274a56e65a3c.hot-update.js",
    "/js/app.00bb25229dd1860b55bf.hot-update.js": "/js/app.00bb25229dd1860b55bf.hot-update.js",
    "/js/app.a455457b89516b0f014c.hot-update.js": "/js/app.a455457b89516b0f014c.hot-update.js",
    "/js/app.b2548afb0188b7fa333a.hot-update.js": "/js/app.b2548afb0188b7fa333a.hot-update.js",
    "/js/app.7bf8b855728c31bd5b92.hot-update.js": "/js/app.7bf8b855728c31bd5b92.hot-update.js",
    "/js/app.169f1afd97e12552cc9f.hot-update.js": "/js/app.169f1afd97e12552cc9f.hot-update.js",
    "/js/app.dd496c921b0391663abb.hot-update.js": "/js/app.dd496c921b0391663abb.hot-update.js",
    "/js/app.a4d24418aff09fd142ea.hot-update.js": "/js/app.a4d24418aff09fd142ea.hot-update.js",
    "/js/app.06b4741fe448bc16fdf6.hot-update.js": "/js/app.06b4741fe448bc16fdf6.hot-update.js",
    "/js/app.23dc43da4119235ffe16.hot-update.js": "/js/app.23dc43da4119235ffe16.hot-update.js",
    "/js/app.2130e61e8daa8bb3c504.hot-update.js": "/js/app.2130e61e8daa8bb3c504.hot-update.js",
    "/js/app.00b4a024641be288243c.hot-update.js": "/js/app.00b4a024641be288243c.hot-update.js",
    "/js/app.7cf279b30a66a5f91828.hot-update.js": "/js/app.7cf279b30a66a5f91828.hot-update.js",
    "/js/app.0975f68ab9b2ae102b0c.hot-update.js": "/js/app.0975f68ab9b2ae102b0c.hot-update.js",
    "/js/app.07cfd1c671a4f8cda4ba.hot-update.js": "/js/app.07cfd1c671a4f8cda4ba.hot-update.js",
    "/js/app.2b4c14d589fbef0317ef.hot-update.js": "/js/app.2b4c14d589fbef0317ef.hot-update.js",
    "/js/app.f68c8bdbdbd02ab6029f.hot-update.js": "/js/app.f68c8bdbdbd02ab6029f.hot-update.js",
    "/js/app.95a1bdd7919a088a23d6.hot-update.js": "/js/app.95a1bdd7919a088a23d6.hot-update.js",
    "/js/app.8df68245fc92c3b27ba5.hot-update.js": "/js/app.8df68245fc92c3b27ba5.hot-update.js",
    "/js/app.4e0a6372a288d7f63059.hot-update.js": "/js/app.4e0a6372a288d7f63059.hot-update.js",
    "/js/app.fe9a38bffe2de1df9a74.hot-update.js": "/js/app.fe9a38bffe2de1df9a74.hot-update.js",
    "/js/app.09d7cbb5ad90d7e74c23.hot-update.js": "/js/app.09d7cbb5ad90d7e74c23.hot-update.js",
    "/js/app.5bd01478cd171ac26932.hot-update.js": "/js/app.5bd01478cd171ac26932.hot-update.js",
    "/js/app.10853ac64eaf4ffab401.hot-update.js": "/js/app.10853ac64eaf4ffab401.hot-update.js",
    "/js/app.525ead43c4b9aa6028c5.hot-update.js": "/js/app.525ead43c4b9aa6028c5.hot-update.js",
    "/js/app.1c22ac8cc8478e8602da.hot-update.js": "/js/app.1c22ac8cc8478e8602da.hot-update.js",
    "/js/app.5d29a76b6b73e9821585.hot-update.js": "/js/app.5d29a76b6b73e9821585.hot-update.js",
    "/js/app.35db183a03de9eae2251.hot-update.js": "/js/app.35db183a03de9eae2251.hot-update.js",
    "/js/app.24e296d09d5b1b1c407e.hot-update.js": "/js/app.24e296d09d5b1b1c407e.hot-update.js",
    "/js/app.0115222780b666baf488.hot-update.js": "/js/app.0115222780b666baf488.hot-update.js",
    "/js/app.c289c949aa333422570e.hot-update.js": "/js/app.c289c949aa333422570e.hot-update.js",
    "/js/app.96f0b4c9bd103862b47c.hot-update.js": "/js/app.96f0b4c9bd103862b47c.hot-update.js",
    "/js/app.a0ccdfd41a934a8e0228.hot-update.js": "/js/app.a0ccdfd41a934a8e0228.hot-update.js",
    "/js/app.d7e492c3aea1f86a36bd.hot-update.js": "/js/app.d7e492c3aea1f86a36bd.hot-update.js",
    "/js/app.1f6b5bfb2951966ef1c2.hot-update.js": "/js/app.1f6b5bfb2951966ef1c2.hot-update.js",
    "/js/app.b49e0f96a3373094d1e7.hot-update.js": "/js/app.b49e0f96a3373094d1e7.hot-update.js",
    "/js/app.e6e527026640de6b22e3.hot-update.js": "/js/app.e6e527026640de6b22e3.hot-update.js",
    "/js/app.8c1d796c11182d78bbe9.hot-update.js": "/js/app.8c1d796c11182d78bbe9.hot-update.js",
    "/js/app.ca74845634ca8fabaafa.hot-update.js": "/js/app.ca74845634ca8fabaafa.hot-update.js",
    "/js/app.466ef0969b9a869cef1a.hot-update.js": "/js/app.466ef0969b9a869cef1a.hot-update.js",
    "/js/app.37dd67a1aa07d23c9918.hot-update.js": "/js/app.37dd67a1aa07d23c9918.hot-update.js",
    "/js/app.09099121c7764b133ec0.hot-update.js": "/js/app.09099121c7764b133ec0.hot-update.js",
    "/js/app.417d417b5a183634d3d9.hot-update.js": "/js/app.417d417b5a183634d3d9.hot-update.js",
    "/js/app.278a20fa26ef33f619fb.hot-update.js": "/js/app.278a20fa26ef33f619fb.hot-update.js",
    "/js/app.c8345fc0562844b7a495.hot-update.js": "/js/app.c8345fc0562844b7a495.hot-update.js",
    "/js/app.f833a7dad34c9ad35923.hot-update.js": "/js/app.f833a7dad34c9ad35923.hot-update.js",
    "/js/app.2faf6a8840a8242d34d2.hot-update.js": "/js/app.2faf6a8840a8242d34d2.hot-update.js",
    "/js/app.ab1b3d3e79f2423a459e.hot-update.js": "/js/app.ab1b3d3e79f2423a459e.hot-update.js",
    "/js/app.1a6699e3cce8d845a828.hot-update.js": "/js/app.1a6699e3cce8d845a828.hot-update.js",
    "/js/app.2425f06939ea85c867ca.hot-update.js": "/js/app.2425f06939ea85c867ca.hot-update.js",
    "/js/app.3d41b35ef7350a096262.hot-update.js": "/js/app.3d41b35ef7350a096262.hot-update.js",
    "/js/app.91e7ac3cb32d92a08b11.hot-update.js": "/js/app.91e7ac3cb32d92a08b11.hot-update.js",
    "/js/app.8d7f64e9fb73704b501a.hot-update.js": "/js/app.8d7f64e9fb73704b501a.hot-update.js",
    "/js/app.bf721707a1e3c97421ec.hot-update.js": "/js/app.bf721707a1e3c97421ec.hot-update.js",
    "/js/app.74545504c413e16ca1ae.hot-update.js": "/js/app.74545504c413e16ca1ae.hot-update.js",
    "/js/app.0f6bc47b29032417c4a1.hot-update.js": "/js/app.0f6bc47b29032417c4a1.hot-update.js",
    "/js/app.0ac4dd7b6c36f9dd66ad.hot-update.js": "/js/app.0ac4dd7b6c36f9dd66ad.hot-update.js",
    "/js/app.f38fda8eaf18330703b7.hot-update.js": "/js/app.f38fda8eaf18330703b7.hot-update.js",
    "/js/app.0d0e35dcbfc075269702.hot-update.js": "/js/app.0d0e35dcbfc075269702.hot-update.js",
    "/js/app.c6322b613f2cd8d31c8b.hot-update.js": "/js/app.c6322b613f2cd8d31c8b.hot-update.js",
    "/js/app.bb45e2be65b3c56f10d9.hot-update.js": "/js/app.bb45e2be65b3c56f10d9.hot-update.js",
    "/js/app.fc9079d86385521736e1.hot-update.js": "/js/app.fc9079d86385521736e1.hot-update.js",
    "/js/app.ffdd609d0a557b1a11ed.hot-update.js": "/js/app.ffdd609d0a557b1a11ed.hot-update.js",
    "/js/app.eeb62daaa7f5a446cc3e.hot-update.js": "/js/app.eeb62daaa7f5a446cc3e.hot-update.js",
    "/js/app.6b13dfca4c3bbca25534.hot-update.js": "/js/app.6b13dfca4c3bbca25534.hot-update.js",
    "/js/app.8757d3bbc0f53446fb81.hot-update.js": "/js/app.8757d3bbc0f53446fb81.hot-update.js",
    "/js/app.623586e92f68ae03eadd.hot-update.js": "/js/app.623586e92f68ae03eadd.hot-update.js",
    "/js/app.5c43d02747724b00ce80.hot-update.js": "/js/app.5c43d02747724b00ce80.hot-update.js",
    "/js/app.bb8a228105071f4f9555.hot-update.js": "/js/app.bb8a228105071f4f9555.hot-update.js",
    "/js/app.b28ce3e1301fce45c92a.hot-update.js": "/js/app.b28ce3e1301fce45c92a.hot-update.js",
    "/js/app.0b6ffa2aabfb95fb44df.hot-update.js": "/js/app.0b6ffa2aabfb95fb44df.hot-update.js",
    "/js/app.6b0e68417cf4058cf5db.hot-update.js": "/js/app.6b0e68417cf4058cf5db.hot-update.js",
    "/js/app.85ee5dc0a069a86a5810.hot-update.js": "/js/app.85ee5dc0a069a86a5810.hot-update.js",
    "/js/app.aaacedab5d4a56ee0541.hot-update.js": "/js/app.aaacedab5d4a56ee0541.hot-update.js",
    "/js/app.820ff01d9df7dfa03cda.hot-update.js": "/js/app.820ff01d9df7dfa03cda.hot-update.js",
    "/js/app.a36b0b4d73a8d3339966.hot-update.js": "/js/app.a36b0b4d73a8d3339966.hot-update.js",
    "/js/app.0994f3317c7b612b6840.hot-update.js": "/js/app.0994f3317c7b612b6840.hot-update.js",
    "/js/app.9542dac396a275a47e8a.hot-update.js": "/js/app.9542dac396a275a47e8a.hot-update.js",
    "/js/app.3f6db270e41563700ee9.hot-update.js": "/js/app.3f6db270e41563700ee9.hot-update.js",
    "/js/app.e282b018e06566962511.hot-update.js": "/js/app.e282b018e06566962511.hot-update.js",
    "/js/app.cd9b057b7fde2cb9561a.hot-update.js": "/js/app.cd9b057b7fde2cb9561a.hot-update.js",
    "/js/app.769b9d3a17d4c2005134.hot-update.js": "/js/app.769b9d3a17d4c2005134.hot-update.js",
    "/js/app.42ad657607c9726920e6.hot-update.js": "/js/app.42ad657607c9726920e6.hot-update.js",
    "/js/app.80058704c9d01c155574.hot-update.js": "/js/app.80058704c9d01c155574.hot-update.js",
    "/js/app.a2c2243943092cd1ea95.hot-update.js": "/js/app.a2c2243943092cd1ea95.hot-update.js",
    "/js/app.eb5adb7c28708b7f986c.hot-update.js": "/js/app.eb5adb7c28708b7f986c.hot-update.js",
    "/js/app.e7be69d11cc0b32a27b1.hot-update.js": "/js/app.e7be69d11cc0b32a27b1.hot-update.js",
    "/js/app.e2f58f50b6ef48076a90.hot-update.js": "/js/app.e2f58f50b6ef48076a90.hot-update.js",
    "/js/app.584a18c70c5f16106465.hot-update.js": "/js/app.584a18c70c5f16106465.hot-update.js",
    "/js/app.805c8314144b078c3427.hot-update.js": "/js/app.805c8314144b078c3427.hot-update.js",
    "/js/app.0a3df6c04e09fc2523fd.hot-update.js": "/js/app.0a3df6c04e09fc2523fd.hot-update.js",
    "/js/app.6125131da4f35b25c695.hot-update.js": "/js/app.6125131da4f35b25c695.hot-update.js",
    "/js/app.f8660e55c55b63c9f60a.hot-update.js": "/js/app.f8660e55c55b63c9f60a.hot-update.js",
    "/js/app.abd222fb0667b0ab4ee8.hot-update.js": "/js/app.abd222fb0667b0ab4ee8.hot-update.js",
    "/js/app.e865e3d4184d55233df1.hot-update.js": "/js/app.e865e3d4184d55233df1.hot-update.js",
    "/js/app.00c2d804bd5096f78573.hot-update.js": "/js/app.00c2d804bd5096f78573.hot-update.js",
    "/js/app.5ce7928f34215186d5c2.hot-update.js": "/js/app.5ce7928f34215186d5c2.hot-update.js",
    "/js/app.dcdc9038de9da404c872.hot-update.js": "/js/app.dcdc9038de9da404c872.hot-update.js",
    "/js/app.6105155f265ab432022a.hot-update.js": "/js/app.6105155f265ab432022a.hot-update.js",
    "/js/app.ea097f8433cc7b2bb7d8.hot-update.js": "/js/app.ea097f8433cc7b2bb7d8.hot-update.js",
    "/js/app.73c9c3b2c8dd60bb58c9.hot-update.js": "/js/app.73c9c3b2c8dd60bb58c9.hot-update.js",
    "/js/app.0d085219b51b4cd2bc53.hot-update.js": "/js/app.0d085219b51b4cd2bc53.hot-update.js",
    "/js/app.ff3762cc453798946e1d.hot-update.js": "/js/app.ff3762cc453798946e1d.hot-update.js",
    "/js/app.92d63c79751b2013301c.hot-update.js": "/js/app.92d63c79751b2013301c.hot-update.js",
    "/js/app.2fa0c75973bf29aa86dc.hot-update.js": "/js/app.2fa0c75973bf29aa86dc.hot-update.js",
    "/js/app.c94bf9b82a39ccfa36e0.hot-update.js": "/js/app.c94bf9b82a39ccfa36e0.hot-update.js",
    "/js/app.ab950f71524adccc5d42.hot-update.js": "/js/app.ab950f71524adccc5d42.hot-update.js",
    "/js/app.4187b916bf9a79a04d5d.hot-update.js": "/js/app.4187b916bf9a79a04d5d.hot-update.js",
    "/js/app.b65ffb7248c9909ddc9f.hot-update.js": "/js/app.b65ffb7248c9909ddc9f.hot-update.js",
    "/js/app.821bd62d75c6111d9925.hot-update.js": "/js/app.821bd62d75c6111d9925.hot-update.js",
    "/js/app.b0ef67500189b9999308.hot-update.js": "/js/app.b0ef67500189b9999308.hot-update.js",
    "/js/app.7330f9eb5a71fed92cb6.hot-update.js": "/js/app.7330f9eb5a71fed92cb6.hot-update.js",
    "/js/app.dddd2079f8cf3a8f59ac.hot-update.js": "/js/app.dddd2079f8cf3a8f59ac.hot-update.js",
    "/js/app.60b51820b4aa4223102b.hot-update.js": "/js/app.60b51820b4aa4223102b.hot-update.js",
    "/js/app.f33f7d2315285154c20a.hot-update.js": "/js/app.f33f7d2315285154c20a.hot-update.js",
    "/js/app.7cdb16168762aef16dc9.hot-update.js": "/js/app.7cdb16168762aef16dc9.hot-update.js",
    "/js/app.6be21981e2b3bd4a9e7d.hot-update.js": "/js/app.6be21981e2b3bd4a9e7d.hot-update.js",
    "/js/app.1053a035aa543fb85efb.hot-update.js": "/js/app.1053a035aa543fb85efb.hot-update.js",
    "/js/app.eed894159c34fdf6ae4f.hot-update.js": "/js/app.eed894159c34fdf6ae4f.hot-update.js",
    "/js/app.25cf5f13ccf2dad70ce8.hot-update.js": "/js/app.25cf5f13ccf2dad70ce8.hot-update.js",
    "/js/app.71161199d9c8fb194be0.hot-update.js": "/js/app.71161199d9c8fb194be0.hot-update.js",
    "/js/app.bb844e89292790731dc3.hot-update.js": "/js/app.bb844e89292790731dc3.hot-update.js",
    "/js/app.f1a694c36129f54d880c.hot-update.js": "/js/app.f1a694c36129f54d880c.hot-update.js",
    "/js/app.e9d9e4ae705626790148.hot-update.js": "/js/app.e9d9e4ae705626790148.hot-update.js",
    "/js/app.2184fffde651dcfcfdfd.hot-update.js": "/js/app.2184fffde651dcfcfdfd.hot-update.js",
    "/js/app.6592104df0b0dac75df2.hot-update.js": "/js/app.6592104df0b0dac75df2.hot-update.js",
    "/js/app.d2f78f36e78d07d65702.hot-update.js": "/js/app.d2f78f36e78d07d65702.hot-update.js",
    "/js/app.0ceff6e6a1693ac321d3.hot-update.js": "/js/app.0ceff6e6a1693ac321d3.hot-update.js",
    "/js/app.484c7f3324ec846ee72e.hot-update.js": "/js/app.484c7f3324ec846ee72e.hot-update.js",
    "/js/app.79568608763e49acc27d.hot-update.js": "/js/app.79568608763e49acc27d.hot-update.js",
    "/js/app.e5973a56236172793df3.hot-update.js": "/js/app.e5973a56236172793df3.hot-update.js",
    "/js/app.04585a03adfc1ec17d82.hot-update.js": "/js/app.04585a03adfc1ec17d82.hot-update.js",
    "/js/app.70caefa73d13eaeffa0f.hot-update.js": "/js/app.70caefa73d13eaeffa0f.hot-update.js",
    "/js/app.da8bacdc1edcb57a47e3.hot-update.js": "/js/app.da8bacdc1edcb57a47e3.hot-update.js",
    "/js/app.67a27259980c91a0fad6.hot-update.js": "/js/app.67a27259980c91a0fad6.hot-update.js",
    "/js/app.8ae03e427eb75886caf8.hot-update.js": "/js/app.8ae03e427eb75886caf8.hot-update.js",
    "/js/app.9c14aaca0bc178a3a1cc.hot-update.js": "/js/app.9c14aaca0bc178a3a1cc.hot-update.js",
    "/js/app.64bff4781bf6a56a99ef.hot-update.js": "/js/app.64bff4781bf6a56a99ef.hot-update.js",
    "/js/app.11b7c0fcf72b9234d372.hot-update.js": "/js/app.11b7c0fcf72b9234d372.hot-update.js",
    "/js/app.02c00756cc87f1d2e5c4.hot-update.js": "/js/app.02c00756cc87f1d2e5c4.hot-update.js",
    "/js/app.e3b1bea97d7610ba1182.hot-update.js": "/js/app.e3b1bea97d7610ba1182.hot-update.js",
    "/js/app.3d5ebdfe421d5053a507.hot-update.js": "/js/app.3d5ebdfe421d5053a507.hot-update.js",
    "/js/app.895a41ddde0267b4d922.hot-update.js": "/js/app.895a41ddde0267b4d922.hot-update.js",
    "/js/app.4fbf75337a596c6dcecb.hot-update.js": "/js/app.4fbf75337a596c6dcecb.hot-update.js",
    "/js/app.e796874f020b11cc6c50.hot-update.js": "/js/app.e796874f020b11cc6c50.hot-update.js",
    "/js/app.8b9daf722b7ec183db93.hot-update.js": "/js/app.8b9daf722b7ec183db93.hot-update.js",
    "/js/app.a5f189d450ecb38d3a2c.hot-update.js": "/js/app.a5f189d450ecb38d3a2c.hot-update.js",
    "/js/app.744eceef8560c285afa4.hot-update.js": "/js/app.744eceef8560c285afa4.hot-update.js",
    "/js/app.0f4d3a348330c1b3c30e.hot-update.js": "/js/app.0f4d3a348330c1b3c30e.hot-update.js",
    "/js/app.109e5beb2c2bd8b4d751.hot-update.js": "/js/app.109e5beb2c2bd8b4d751.hot-update.js",
    "/js/app.e866b9d0b467b7515cb0.hot-update.js": "/js/app.e866b9d0b467b7515cb0.hot-update.js",
    "/js/app.dbf3c33f3078ba515ab8.hot-update.js": "/js/app.dbf3c33f3078ba515ab8.hot-update.js",
    "/js/app.67806275cd5ae25f5092.hot-update.js": "/js/app.67806275cd5ae25f5092.hot-update.js",
    "/js/app.5ff3997ad3aae31ca0ab.hot-update.js": "/js/app.5ff3997ad3aae31ca0ab.hot-update.js",
    "/js/app.e86eb5cf3c56f89a45d5.hot-update.js": "/js/app.e86eb5cf3c56f89a45d5.hot-update.js",
    "/js/app.fd372271092b39382ddf.hot-update.js": "/js/app.fd372271092b39382ddf.hot-update.js",
    "/js/app.3819b1bed2d93def346f.hot-update.js": "/js/app.3819b1bed2d93def346f.hot-update.js",
    "/js/app.3ae076107070d71c9f14.hot-update.js": "/js/app.3ae076107070d71c9f14.hot-update.js",
    "/js/app.2c324ce1f235dc3ddad1.hot-update.js": "/js/app.2c324ce1f235dc3ddad1.hot-update.js",
    "/js/app.553487df585b996faeb7.hot-update.js": "/js/app.553487df585b996faeb7.hot-update.js",
    "/js/app.2de47823f63937c2a23b.hot-update.js": "/js/app.2de47823f63937c2a23b.hot-update.js",
    "/js/app.699655401351f82b4013.hot-update.js": "/js/app.699655401351f82b4013.hot-update.js",
    "/js/app.1fb475d809e2916d002d.hot-update.js": "/js/app.1fb475d809e2916d002d.hot-update.js",
    "/js/app.488dce5d75e75c5e7e99.hot-update.js": "/js/app.488dce5d75e75c5e7e99.hot-update.js",
    "/js/app.b909039c7e79ac9752d7.hot-update.js": "/js/app.b909039c7e79ac9752d7.hot-update.js",
    "/js/app.f73c0146b8219598f885.hot-update.js": "/js/app.f73c0146b8219598f885.hot-update.js",
    "/js/app.4b9824000cec2e84dfaf.hot-update.js": "/js/app.4b9824000cec2e84dfaf.hot-update.js",
    "/js/app.3898b79c7fd50d7188fb.hot-update.js": "/js/app.3898b79c7fd50d7188fb.hot-update.js",
    "/js/app.f60e0c70cb15534b8b2c.hot-update.js": "/js/app.f60e0c70cb15534b8b2c.hot-update.js",
    "/js/app.4e7bbc658edb60432656.hot-update.js": "/js/app.4e7bbc658edb60432656.hot-update.js",
    "/js/app.02eb0fa2117d6366abec.hot-update.js": "/js/app.02eb0fa2117d6366abec.hot-update.js",
    "/js/app.b7cc5b3d741b8e235173.hot-update.js": "/js/app.b7cc5b3d741b8e235173.hot-update.js",
    "/js/app.7222520f6d2ab5ea4775.hot-update.js": "/js/app.7222520f6d2ab5ea4775.hot-update.js",
    "/js/app.c3ef01c8cf25d11b7e04.hot-update.js": "/js/app.c3ef01c8cf25d11b7e04.hot-update.js",
    "/js/app.42ecdb466577d8a4b2f3.hot-update.js": "/js/app.42ecdb466577d8a4b2f3.hot-update.js",
    "/js/app.7d4da2b599585d020a18.hot-update.js": "/js/app.7d4da2b599585d020a18.hot-update.js",
    "/js/app.f47b9871fddbdd2a134a.hot-update.js": "/js/app.f47b9871fddbdd2a134a.hot-update.js",
    "/js/app.c448f4dde6307367d651.hot-update.js": "/js/app.c448f4dde6307367d651.hot-update.js",
    "/js/app.bd7895b09081420fc309.hot-update.js": "/js/app.bd7895b09081420fc309.hot-update.js",
    "/js/app.95ff26d35fcf048424d6.hot-update.js": "/js/app.95ff26d35fcf048424d6.hot-update.js",
    "/js/app.180fdca430101d3268d9.hot-update.js": "/js/app.180fdca430101d3268d9.hot-update.js",
    "/js/app.e6226a91930c2a5b5082.hot-update.js": "/js/app.e6226a91930c2a5b5082.hot-update.js",
    "/js/app.e4a2c22eced634632111.hot-update.js": "/js/app.e4a2c22eced634632111.hot-update.js",
    "/js/app.af1bc05f5646ff0221e1.hot-update.js": "/js/app.af1bc05f5646ff0221e1.hot-update.js",
    "/js/app.15f51b9dac19e0c27f41.hot-update.js": "/js/app.15f51b9dac19e0c27f41.hot-update.js",
    "/js/app.106d5e587870e3822e71.hot-update.js": "/js/app.106d5e587870e3822e71.hot-update.js",
    "/js/app.9af36ecf4cf7da0ed644.hot-update.js": "/js/app.9af36ecf4cf7da0ed644.hot-update.js",
    "/js/app.a43da041d3bbd1c02e4e.hot-update.js": "/js/app.a43da041d3bbd1c02e4e.hot-update.js",
    "/js/app.94b0f46fbd8b1f45889a.hot-update.js": "/js/app.94b0f46fbd8b1f45889a.hot-update.js",
    "/js/app.a4f4fc32ac818422b643.hot-update.js": "/js/app.a4f4fc32ac818422b643.hot-update.js",
    "/js/app.b7e70640631ea6e5f4d4.hot-update.js": "/js/app.b7e70640631ea6e5f4d4.hot-update.js",
    "/js/app.8d4fef632ee9a69a5b30.hot-update.js": "/js/app.8d4fef632ee9a69a5b30.hot-update.js",
    "/js/app.45810f576c09d1573d47.hot-update.js": "/js/app.45810f576c09d1573d47.hot-update.js",
    "/js/app.b4c95f95b59a14c27fdc.hot-update.js": "/js/app.b4c95f95b59a14c27fdc.hot-update.js",
    "/js/app.44c87cef1313457448ce.hot-update.js": "/js/app.44c87cef1313457448ce.hot-update.js",
    "/js/app.e33b7bfadf43902f2b5b.hot-update.js": "/js/app.e33b7bfadf43902f2b5b.hot-update.js",
    "/js/app.07bf8d47e9db5c9c72ef.hot-update.js": "/js/app.07bf8d47e9db5c9c72ef.hot-update.js",
    "/js/app.bec230de6f437b52da01.hot-update.js": "/js/app.bec230de6f437b52da01.hot-update.js",
    "/js/app.ba5930716fba4d431b94.hot-update.js": "/js/app.ba5930716fba4d431b94.hot-update.js",
    "/js/app.9e6cc62be94a19a678f9.hot-update.js": "/js/app.9e6cc62be94a19a678f9.hot-update.js",
    "/js/app.61e2c461ef0574ecd2fd.hot-update.js": "/js/app.61e2c461ef0574ecd2fd.hot-update.js",
    "/js/app.ccdd761421ca05a1d52f.hot-update.js": "/js/app.ccdd761421ca05a1d52f.hot-update.js",
    "/js/app.48ec4254e5f67bd8f978.hot-update.js": "/js/app.48ec4254e5f67bd8f978.hot-update.js",
    "/js/app.ca9ab6247d0f9dab9df8.hot-update.js": "/js/app.ca9ab6247d0f9dab9df8.hot-update.js",
    "/js/app.38e008d9129330021f2b.hot-update.js": "/js/app.38e008d9129330021f2b.hot-update.js",
    "/js/app.e30150656c85ace6ec70.hot-update.js": "/js/app.e30150656c85ace6ec70.hot-update.js",
    "/js/app.7bc3cd3b6a1c13d033b6.hot-update.js": "/js/app.7bc3cd3b6a1c13d033b6.hot-update.js",
    "/js/app.a5e335b0e75165427128.hot-update.js": "/js/app.a5e335b0e75165427128.hot-update.js",
    "/js/app.5655a793aafdc81ef73f.hot-update.js": "/js/app.5655a793aafdc81ef73f.hot-update.js",
    "/js/app.ae3e67c2477f53bb93b5.hot-update.js": "/js/app.ae3e67c2477f53bb93b5.hot-update.js",
    "/js/app.5f2ac1807dfaf23a00dc.hot-update.js": "/js/app.5f2ac1807dfaf23a00dc.hot-update.js",
    "/js/app.c66cb6d6deae208a445b.hot-update.js": "/js/app.c66cb6d6deae208a445b.hot-update.js",
    "/js/app.d34b4fd193ad51d6e271.hot-update.js": "/js/app.d34b4fd193ad51d6e271.hot-update.js",
    "/js/app.44fdfdb4d1417794b6e0.hot-update.js": "/js/app.44fdfdb4d1417794b6e0.hot-update.js",
    "/js/app.d1f6083d2f427e14842d.hot-update.js": "/js/app.d1f6083d2f427e14842d.hot-update.js",
    "/js/app.6b48bb99ef52d01fb0bc.hot-update.js": "/js/app.6b48bb99ef52d01fb0bc.hot-update.js",
    "/js/app.db7d9bba26e764a41d59.hot-update.js": "/js/app.db7d9bba26e764a41d59.hot-update.js",
    "/js/app.1c00c8cb08685aaa484f.hot-update.js": "/js/app.1c00c8cb08685aaa484f.hot-update.js",
    "/js/app.fa8e52d007ce8748612e.hot-update.js": "/js/app.fa8e52d007ce8748612e.hot-update.js",
    "/js/app.670d4245990566dcfb19.hot-update.js": "/js/app.670d4245990566dcfb19.hot-update.js",
    "/js/app.ae2656f2f9f3a17259c6.hot-update.js": "/js/app.ae2656f2f9f3a17259c6.hot-update.js",
    "/js/app.a5a56c2cc3e8829d7411.hot-update.js": "/js/app.a5a56c2cc3e8829d7411.hot-update.js",
    "/js/app.0e35bd8364956cee7155.hot-update.js": "/js/app.0e35bd8364956cee7155.hot-update.js",
    "/js/app.c3e3b7075993252b5eaf.hot-update.js": "/js/app.c3e3b7075993252b5eaf.hot-update.js",
    "/js/app.af62b211a7fd767ab9e7.hot-update.js": "/js/app.af62b211a7fd767ab9e7.hot-update.js",
    "/js/app.42043a727389fc0612ff.hot-update.js": "/js/app.42043a727389fc0612ff.hot-update.js",
    "/js/app.2ba47484bd58d30c4993.hot-update.js": "/js/app.2ba47484bd58d30c4993.hot-update.js",
    "/js/app.2aea5763f83b7d222e62.hot-update.js": "/js/app.2aea5763f83b7d222e62.hot-update.js",
    "/js/app.65d5e05e2bbbee2953d8.hot-update.js": "/js/app.65d5e05e2bbbee2953d8.hot-update.js",
    "/js/app.511e87df3c7bd860a550.hot-update.js": "/js/app.511e87df3c7bd860a550.hot-update.js",
    "/js/app.4bf39e52c10618078146.hot-update.js": "/js/app.4bf39e52c10618078146.hot-update.js",
    "/js/app.e753ba32351d3968f6b5.hot-update.js": "/js/app.e753ba32351d3968f6b5.hot-update.js",
    "/js/app.983d2d6d325961849b0c.hot-update.js": "/js/app.983d2d6d325961849b0c.hot-update.js",
    "/js/app.3014e0d4f687e14602ac.hot-update.js": "/js/app.3014e0d4f687e14602ac.hot-update.js",
    "/js/app.7147bbb1db509b29ca1c.hot-update.js": "/js/app.7147bbb1db509b29ca1c.hot-update.js",
    "/js/app.b2e7faf2b3e2ecd809e4.hot-update.js": "/js/app.b2e7faf2b3e2ecd809e4.hot-update.js",
    "/js/app.73f943265b7a80c6e5b6.hot-update.js": "/js/app.73f943265b7a80c6e5b6.hot-update.js",
    "/js/app.25c76b5cf957953ae02b.hot-update.js": "/js/app.25c76b5cf957953ae02b.hot-update.js",
    "/js/app.9e97b2a809e93b617fe9.hot-update.js": "/js/app.9e97b2a809e93b617fe9.hot-update.js",
    "/js/app.7bc0ec296ba20db8ad16.hot-update.js": "/js/app.7bc0ec296ba20db8ad16.hot-update.js",
    "/js/app.0472fd750f19cd1fcbe3.hot-update.js": "/js/app.0472fd750f19cd1fcbe3.hot-update.js",
    "/js/app.da33ae1c0952855e714f.hot-update.js": "/js/app.da33ae1c0952855e714f.hot-update.js",
    "/js/app.ff260e68c8c46f4ff551.hot-update.js": "/js/app.ff260e68c8c46f4ff551.hot-update.js",
    "/js/app.4f9e0d02062afcad4fd7.hot-update.js": "/js/app.4f9e0d02062afcad4fd7.hot-update.js",
    "/js/app.384c9a006a13cb343657.hot-update.js": "/js/app.384c9a006a13cb343657.hot-update.js",
    "/js/app.4995b62bfb4f5a964eaa.hot-update.js": "/js/app.4995b62bfb4f5a964eaa.hot-update.js",
    "/js/app.7c3c99c1e15251829be8.hot-update.js": "/js/app.7c3c99c1e15251829be8.hot-update.js",
    "/js/app.c7bd231163f6dcc99bef.hot-update.js": "/js/app.c7bd231163f6dcc99bef.hot-update.js",
    "/js/app.cbef36d4ff4f64727e85.hot-update.js": "/js/app.cbef36d4ff4f64727e85.hot-update.js",
    "/js/app.b4910db9ea960ef03877.hot-update.js": "/js/app.b4910db9ea960ef03877.hot-update.js",
    "/js/app.05616872449acaa493ef.hot-update.js": "/js/app.05616872449acaa493ef.hot-update.js",
    "/js/app.f47a53025bab9f39c9d8.hot-update.js": "/js/app.f47a53025bab9f39c9d8.hot-update.js",
    "/js/app.6e0005aa14bcf6b2255c.hot-update.js": "/js/app.6e0005aa14bcf6b2255c.hot-update.js",
    "/js/app.d2e3e28caaffef1de63a.hot-update.js": "/js/app.d2e3e28caaffef1de63a.hot-update.js",
    "/js/app.cc276dc2ffd3a4d5ce7e.hot-update.js": "/js/app.cc276dc2ffd3a4d5ce7e.hot-update.js",
    "/js/app.5fb941de3c9b10ad311b.hot-update.js": "/js/app.5fb941de3c9b10ad311b.hot-update.js",
    "/js/app.2e7862dd4be35a5d6d54.hot-update.js": "/js/app.2e7862dd4be35a5d6d54.hot-update.js",
    "/js/app.cfa92dd7aec48b2d2fe4.hot-update.js": "/js/app.cfa92dd7aec48b2d2fe4.hot-update.js",
    "/js/app.694a69f7d9d3edf67463.hot-update.js": "/js/app.694a69f7d9d3edf67463.hot-update.js",
    "/js/app.dae16325ef641af82724.hot-update.js": "/js/app.dae16325ef641af82724.hot-update.js",
    "/js/app.2918fde788f6340488ae.hot-update.js": "/js/app.2918fde788f6340488ae.hot-update.js",
    "/js/app.85094dd2607b2d9452ce.hot-update.js": "/js/app.85094dd2607b2d9452ce.hot-update.js",
    "/js/app.881f062f44af6d716b85.hot-update.js": "/js/app.881f062f44af6d716b85.hot-update.js",
    "/js/app.219f648a29f01daac42d.hot-update.js": "/js/app.219f648a29f01daac42d.hot-update.js",
    "/js/app.8e747a8959014317fa1e.hot-update.js": "/js/app.8e747a8959014317fa1e.hot-update.js",
    "/js/app.09a4e2afb7894f4ff04c.hot-update.js": "/js/app.09a4e2afb7894f4ff04c.hot-update.js",
    "/js/app.369e5dd381caa128c23a.hot-update.js": "/js/app.369e5dd381caa128c23a.hot-update.js",
    "/js/app.f19cbdac90b2aa7794c8.hot-update.js": "/js/app.f19cbdac90b2aa7794c8.hot-update.js",
    "/js/app.c15b1a85090a765f24cf.hot-update.js": "/js/app.c15b1a85090a765f24cf.hot-update.js",
    "/js/app.5ea78740230691ff9db3.hot-update.js": "/js/app.5ea78740230691ff9db3.hot-update.js",
    "/js/app.e643e086096fe6600532.hot-update.js": "/js/app.e643e086096fe6600532.hot-update.js",
    "/js/app.c9bac8755149b2a71d4b.hot-update.js": "/js/app.c9bac8755149b2a71d4b.hot-update.js",
    "/js/app.cb80da7a911694996814.hot-update.js": "/js/app.cb80da7a911694996814.hot-update.js",
    "/js/app.74f37c51375c6f7e0a1e.hot-update.js": "/js/app.74f37c51375c6f7e0a1e.hot-update.js",
    "/js/app.901088912f3cca878676.hot-update.js": "/js/app.901088912f3cca878676.hot-update.js",
    "/js/app.369cfe32ae2b450d7662.hot-update.js": "/js/app.369cfe32ae2b450d7662.hot-update.js",
    "/js/app.6d0d9b379eab51b0b311.hot-update.js": "/js/app.6d0d9b379eab51b0b311.hot-update.js",
    "/js/app.693d8cb07a67b94499a2.hot-update.js": "/js/app.693d8cb07a67b94499a2.hot-update.js",
    "/js/app.d86adba21cb041fe13a9.hot-update.js": "/js/app.d86adba21cb041fe13a9.hot-update.js",
    "/js/app.26695d54cd8a9f893324.hot-update.js": "/js/app.26695d54cd8a9f893324.hot-update.js",
    "/js/app.da3f21f05dfed4cf5ca6.hot-update.js": "/js/app.da3f21f05dfed4cf5ca6.hot-update.js",
    "/js/app.9f3e1a9f535b3fd10367.hot-update.js": "/js/app.9f3e1a9f535b3fd10367.hot-update.js",
    "/js/app.f05e97683a8aca1c0d2c.hot-update.js": "/js/app.f05e97683a8aca1c0d2c.hot-update.js",
    "/js/app.c93bccce1920f75c15dc.hot-update.js": "/js/app.c93bccce1920f75c15dc.hot-update.js",
    "/js/app.ad62f00a8f30a324b1a1.hot-update.js": "/js/app.ad62f00a8f30a324b1a1.hot-update.js",
    "/js/app.232454250b2fe2a520cd.hot-update.js": "/js/app.232454250b2fe2a520cd.hot-update.js",
    "/js/app.510129fbf33b6418f363.hot-update.js": "/js/app.510129fbf33b6418f363.hot-update.js",
    "/js/app.771fd56103f64de47438.hot-update.js": "/js/app.771fd56103f64de47438.hot-update.js",
    "/js/app.850f84d6144a7b817fa0.hot-update.js": "/js/app.850f84d6144a7b817fa0.hot-update.js",
    "/js/app.92345e0254e34acf1ce7.hot-update.js": "/js/app.92345e0254e34acf1ce7.hot-update.js",
    "/js/app.f7dc50751913b729e042.hot-update.js": "/js/app.f7dc50751913b729e042.hot-update.js",
    "/js/app.1df9845fb23993080a76.hot-update.js": "/js/app.1df9845fb23993080a76.hot-update.js",
    "/js/app.399a9bde2e7476961a87.hot-update.js": "/js/app.399a9bde2e7476961a87.hot-update.js",
    "/js/app.b0437789a81b879dd264.hot-update.js": "/js/app.b0437789a81b879dd264.hot-update.js",
    "/js/app.549ad436da6922bd793b.hot-update.js": "/js/app.549ad436da6922bd793b.hot-update.js",
    "/js/app.a710591a3941f52d9b84.hot-update.js": "/js/app.a710591a3941f52d9b84.hot-update.js",
    "/js/app.2f32db22d6fad20d01f8.hot-update.js": "/js/app.2f32db22d6fad20d01f8.hot-update.js",
    "/js/app.c2db30cefa813d0425a3.hot-update.js": "/js/app.c2db30cefa813d0425a3.hot-update.js",
    "/js/app.aaae7b7c96d431d88f51.hot-update.js": "/js/app.aaae7b7c96d431d88f51.hot-update.js",
    "/js/app.37a3c1b8f65904bed339.hot-update.js": "/js/app.37a3c1b8f65904bed339.hot-update.js",
    "/js/app.6250ddf33d412c07869d.hot-update.js": "/js/app.6250ddf33d412c07869d.hot-update.js",
    "/js/app.d84de3c87ff3eb5dd874.hot-update.js": "/js/app.d84de3c87ff3eb5dd874.hot-update.js",
    "/js/app.1a89d2cf59748b1eb7f7.hot-update.js": "/js/app.1a89d2cf59748b1eb7f7.hot-update.js",
    "/js/app.d86fa610996733cb890b.hot-update.js": "/js/app.d86fa610996733cb890b.hot-update.js",
    "/js/app.2e56c034c617c16371c0.hot-update.js": "/js/app.2e56c034c617c16371c0.hot-update.js",
    "/js/app.bdbc870298bdd741f500.hot-update.js": "/js/app.bdbc870298bdd741f500.hot-update.js",
    "/js/app.06f1acd68736e2d36ef5.hot-update.js": "/js/app.06f1acd68736e2d36ef5.hot-update.js",
    "/js/app.c79d066c7374520b835d.hot-update.js": "/js/app.c79d066c7374520b835d.hot-update.js",
    "/js/app.756df0723902b0dff24d.hot-update.js": "/js/app.756df0723902b0dff24d.hot-update.js",
    "/js/app.16b80355c188b7ed6bdc.hot-update.js": "/js/app.16b80355c188b7ed6bdc.hot-update.js",
    "/js/app.0e089ad977ca4cc89515.hot-update.js": "/js/app.0e089ad977ca4cc89515.hot-update.js",
    "/js/app.f0c32237ecacb71ba494.hot-update.js": "/js/app.f0c32237ecacb71ba494.hot-update.js",
    "/js/app.92cab9a102755b1d754b.hot-update.js": "/js/app.92cab9a102755b1d754b.hot-update.js",
    "/js/app.0f33d8fde9daac9b9c45.hot-update.js": "/js/app.0f33d8fde9daac9b9c45.hot-update.js",
    "/js/app.92c663f41477de4ae303.hot-update.js": "/js/app.92c663f41477de4ae303.hot-update.js",
    "/js/app.4dd327f4f269c08b2a7d.hot-update.js": "/js/app.4dd327f4f269c08b2a7d.hot-update.js",
    "/js/app.9cb265b9985e807fb769.hot-update.js": "/js/app.9cb265b9985e807fb769.hot-update.js",
    "/js/app.d6401ddda42c1edf5367.hot-update.js": "/js/app.d6401ddda42c1edf5367.hot-update.js",
    "/js/app.0ae18ed0323f3cba995f.hot-update.js": "/js/app.0ae18ed0323f3cba995f.hot-update.js",
    "/js/app.0f5e84152d95ed759973.hot-update.js": "/js/app.0f5e84152d95ed759973.hot-update.js",
    "/js/app.31df992bf79da5527b1c.hot-update.js": "/js/app.31df992bf79da5527b1c.hot-update.js",
    "/js/app.0874b34dc63f4628305d.hot-update.js": "/js/app.0874b34dc63f4628305d.hot-update.js",
    "/js/app.dcce1d03636bb2e05e48.hot-update.js": "/js/app.dcce1d03636bb2e05e48.hot-update.js",
    "/js/app.b3de4c0085535396be70.hot-update.js": "/js/app.b3de4c0085535396be70.hot-update.js",
    "/js/app.6d00a51f91852d918f9a.hot-update.js": "/js/app.6d00a51f91852d918f9a.hot-update.js",
    "/js/app.2d96913b532c53097639.hot-update.js": "/js/app.2d96913b532c53097639.hot-update.js",
    "/js/app.8c2d2b1e8af6d9facea1.hot-update.js": "/js/app.8c2d2b1e8af6d9facea1.hot-update.js",
    "/js/app.5c28d490f81d9fb0bbc4.hot-update.js": "/js/app.5c28d490f81d9fb0bbc4.hot-update.js",
    "/js/app.13de0bed013750d07c42.hot-update.js": "/js/app.13de0bed013750d07c42.hot-update.js",
    "/js/app.e8449ab9149be9d57a0e.hot-update.js": "/js/app.e8449ab9149be9d57a0e.hot-update.js",
    "/js/app.dd76e5f8863b799b4290.hot-update.js": "/js/app.dd76e5f8863b799b4290.hot-update.js",
    "/js/app.35590032c19cdc816820.hot-update.js": "/js/app.35590032c19cdc816820.hot-update.js",
    "/js/app.1c24d2d0ac952e27c610.hot-update.js": "/js/app.1c24d2d0ac952e27c610.hot-update.js",
    "/js/app.802663d34e420e841747.hot-update.js": "/js/app.802663d34e420e841747.hot-update.js",
    "/js/app.d6ac69dc4636a9ecd7d8.hot-update.js": "/js/app.d6ac69dc4636a9ecd7d8.hot-update.js",
    "/js/app.aed329dfdd54fbbecfa3.hot-update.js": "/js/app.aed329dfdd54fbbecfa3.hot-update.js",
    "/js/app.e47dbf44fdfd8e1068d5.hot-update.js": "/js/app.e47dbf44fdfd8e1068d5.hot-update.js",
    "/js/app.db5263cf1a7baec7e752.hot-update.js": "/js/app.db5263cf1a7baec7e752.hot-update.js",
    "/js/app.b4d10dd1e83387e69417.hot-update.js": "/js/app.b4d10dd1e83387e69417.hot-update.js",
    "/js/app.60ee5ee9d667a77072ea.hot-update.js": "/js/app.60ee5ee9d667a77072ea.hot-update.js",
    "/js/app.6f28e611a144502ebb6c.hot-update.js": "/js/app.6f28e611a144502ebb6c.hot-update.js",
    "/js/app.1840eaee83ecab4c7ee9.hot-update.js": "/js/app.1840eaee83ecab4c7ee9.hot-update.js",
    "/js/app.e5354fee389c86a64b99.hot-update.js": "/js/app.e5354fee389c86a64b99.hot-update.js",
    "/js/app.15a6000fdb6781768438.hot-update.js": "/js/app.15a6000fdb6781768438.hot-update.js",
    "/js/app.6fb0fa0d8848644989b4.hot-update.js": "/js/app.6fb0fa0d8848644989b4.hot-update.js",
    "/js/app.0f90507acd094b138bea.hot-update.js": "/js/app.0f90507acd094b138bea.hot-update.js",
    "/js/app.16e07d98e236f36849a6.hot-update.js": "/js/app.16e07d98e236f36849a6.hot-update.js",
    "/js/app.1444999bab23e5774f90.hot-update.js": "/js/app.1444999bab23e5774f90.hot-update.js",
    "/js/app.4c64b2a3aadf1feed26a.hot-update.js": "/js/app.4c64b2a3aadf1feed26a.hot-update.js",
    "/js/app.db085543a56f5c289ac5.hot-update.js": "/js/app.db085543a56f5c289ac5.hot-update.js",
    "/js/app.d8ccbdbf73f44eb9bc1f.hot-update.js": "/js/app.d8ccbdbf73f44eb9bc1f.hot-update.js",
    "/js/app.9c10c0758580e5b59aae.hot-update.js": "/js/app.9c10c0758580e5b59aae.hot-update.js",
    "/js/app.1f5d87c0926348c3a24a.hot-update.js": "/js/app.1f5d87c0926348c3a24a.hot-update.js",
    "/js/app.711e3c4726d943909811.hot-update.js": "/js/app.711e3c4726d943909811.hot-update.js",
    "/js/app.51988fa640d1f7285e83.hot-update.js": "/js/app.51988fa640d1f7285e83.hot-update.js",
    "/js/app.e2231362404b0fb4f966.hot-update.js": "/js/app.e2231362404b0fb4f966.hot-update.js",
    "/js/app.705691be90ba8efb1a8f.hot-update.js": "/js/app.705691be90ba8efb1a8f.hot-update.js",
    "/js/app.c0cfbb19f8c19d2c7ae8.hot-update.js": "/js/app.c0cfbb19f8c19d2c7ae8.hot-update.js",
    "/js/app.c53888d014f82cd02ac9.hot-update.js": "/js/app.c53888d014f82cd02ac9.hot-update.js",
    "/js/app.6b3927ceae3eab09ff80.hot-update.js": "/js/app.6b3927ceae3eab09ff80.hot-update.js",
    "/js/app.fba2b64d4124a6d0ee58.hot-update.js": "/js/app.fba2b64d4124a6d0ee58.hot-update.js",
    "/js/app.245bd8502e5c02e4eb94.hot-update.js": "/js/app.245bd8502e5c02e4eb94.hot-update.js",
    "/js/app.4d50458115e8e9a4c2fb.hot-update.js": "/js/app.4d50458115e8e9a4c2fb.hot-update.js",
    "/js/app.1fdeb008c78fd58adc20.hot-update.js": "/js/app.1fdeb008c78fd58adc20.hot-update.js",
    "/js/app.3323b8f20c2ca23783b0.hot-update.js": "/js/app.3323b8f20c2ca23783b0.hot-update.js",
    "/js/app.ad6d1c5d67622a2e7fd4.hot-update.js": "/js/app.ad6d1c5d67622a2e7fd4.hot-update.js",
    "/js/app.aa1ece65bd409c0a6de1.hot-update.js": "/js/app.aa1ece65bd409c0a6de1.hot-update.js",
    "/js/app.6f94b6b2245a4c68a842.hot-update.js": "/js/app.6f94b6b2245a4c68a842.hot-update.js",
    "/js/app.7f6147e379d4d8b3eae2.hot-update.js": "/js/app.7f6147e379d4d8b3eae2.hot-update.js",
    "/js/app.c482a4dc353ae71f6954.hot-update.js": "/js/app.c482a4dc353ae71f6954.hot-update.js",
    "/js/app.e5c1e447137803c0ea1a.hot-update.js": "/js/app.e5c1e447137803c0ea1a.hot-update.js",
    "/js/app.825fff490282c49f0f42.hot-update.js": "/js/app.825fff490282c49f0f42.hot-update.js",
    "/js/app.df14db745d5f305c6ea6.hot-update.js": "/js/app.df14db745d5f305c6ea6.hot-update.js",
    "/js/app.a25fc61440d91520096e.hot-update.js": "/js/app.a25fc61440d91520096e.hot-update.js",
    "/js/app.df9a5ed74cd8b651639d.hot-update.js": "/js/app.df9a5ed74cd8b651639d.hot-update.js",
    "/js/app.6daacbcfed29b4475324.hot-update.js": "/js/app.6daacbcfed29b4475324.hot-update.js",
    "/js/app.8f1588bd543a025ee9ff.hot-update.js": "/js/app.8f1588bd543a025ee9ff.hot-update.js",
    "/js/app.befeeba374b3d055f069.hot-update.js": "/js/app.befeeba374b3d055f069.hot-update.js",
    "/js/app.1388f4480c4f489f9c2e.hot-update.js": "/js/app.1388f4480c4f489f9c2e.hot-update.js",
    "/js/app.7d1e88401516107a8b21.hot-update.js": "/js/app.7d1e88401516107a8b21.hot-update.js",
    "/js/app.44cf089522427a061baf.hot-update.js": "/js/app.44cf089522427a061baf.hot-update.js",
    "/js/app.3c8edb06471cf422581c.hot-update.js": "/js/app.3c8edb06471cf422581c.hot-update.js",
    "/js/app.8f4d93c4b665ca47ff1c.hot-update.js": "/js/app.8f4d93c4b665ca47ff1c.hot-update.js",
    "/js/app.822a88f9e45be8026cba.hot-update.js": "/js/app.822a88f9e45be8026cba.hot-update.js",
    "/js/app.7cc21ff7b98a2b24ce28.hot-update.js": "/js/app.7cc21ff7b98a2b24ce28.hot-update.js",
    "/js/app.257a66c7ad1d6a40117c.hot-update.js": "/js/app.257a66c7ad1d6a40117c.hot-update.js",
    "/js/app.8f3635ab9e1741610b6a.hot-update.js": "/js/app.8f3635ab9e1741610b6a.hot-update.js",
    "/js/app.5803e0e3632fe3ba57e1.hot-update.js": "/js/app.5803e0e3632fe3ba57e1.hot-update.js",
    "/js/app.63c4272ddd1b30f09767.hot-update.js": "/js/app.63c4272ddd1b30f09767.hot-update.js",
    "/js/app.70c5cdfb6676745f3e84.hot-update.js": "/js/app.70c5cdfb6676745f3e84.hot-update.js",
    "/js/app.46c59c98714896333e85.hot-update.js": "/js/app.46c59c98714896333e85.hot-update.js",
    "/js/app.cb49962e0f60fdebbac1.hot-update.js": "/js/app.cb49962e0f60fdebbac1.hot-update.js",
    "/js/app.4beec343bcf23b1e3595.hot-update.js": "/js/app.4beec343bcf23b1e3595.hot-update.js",
    "/js/app.66073c50932f5b234fa6.hot-update.js": "/js/app.66073c50932f5b234fa6.hot-update.js",
    "/js/app.3040922194bf559f0239.hot-update.js": "/js/app.3040922194bf559f0239.hot-update.js",
    "/js/app.39c547be30ab90cb8975.hot-update.js": "/js/app.39c547be30ab90cb8975.hot-update.js",
    "/js/app.0b14ae7bca8673af4934.hot-update.js": "/js/app.0b14ae7bca8673af4934.hot-update.js",
    "/js/app.820c7078bb0653fdbffc.hot-update.js": "/js/app.820c7078bb0653fdbffc.hot-update.js",
    "/js/app.3326d56e7a5ad11ec925.hot-update.js": "/js/app.3326d56e7a5ad11ec925.hot-update.js",
    "/js/app.580fc22d56b89a5534c9.hot-update.js": "/js/app.580fc22d56b89a5534c9.hot-update.js",
    "/js/app.bd3b5ab17e32599b8271.hot-update.js": "/js/app.bd3b5ab17e32599b8271.hot-update.js",
    "/js/app.8942a49af8742f4388ae.hot-update.js": "/js/app.8942a49af8742f4388ae.hot-update.js",
    "/js/app.e85e9bc1bdd4e402ebe3.hot-update.js": "/js/app.e85e9bc1bdd4e402ebe3.hot-update.js",
    "/js/app.5219e246e2a82af515aa.hot-update.js": "/js/app.5219e246e2a82af515aa.hot-update.js",
    "/js/app.da7da47130126b7f8f8b.hot-update.js": "/js/app.da7da47130126b7f8f8b.hot-update.js",
    "/js/app.0630b7cfeb04bb9c404a.hot-update.js": "/js/app.0630b7cfeb04bb9c404a.hot-update.js",
    "/js/app.cfdd7922241c082689e2.hot-update.js": "/js/app.cfdd7922241c082689e2.hot-update.js",
    "/js/app.f0e02cf5d4c907a9afb6.hot-update.js": "/js/app.f0e02cf5d4c907a9afb6.hot-update.js",
    "/js/app.3f117e42428ff4e77c43.hot-update.js": "/js/app.3f117e42428ff4e77c43.hot-update.js",
    "/js/app.d642646b294398384d11.hot-update.js": "/js/app.d642646b294398384d11.hot-update.js",
    "/js/app.e57fee6ef569ec7de430.hot-update.js": "/js/app.e57fee6ef569ec7de430.hot-update.js",
    "/js/app.772d4026ca51b72d925a.hot-update.js": "/js/app.772d4026ca51b72d925a.hot-update.js",
    "/js/app.5a489d90d1893673dcb1.hot-update.js": "/js/app.5a489d90d1893673dcb1.hot-update.js",
    "/js/app.b3bed5399be9385e2534.hot-update.js": "/js/app.b3bed5399be9385e2534.hot-update.js",
    "/js/app.b4875d3d6d0badc5b8ca.hot-update.js": "/js/app.b4875d3d6d0badc5b8ca.hot-update.js",
    "/js/app.a992ed7b22bd9b87b6db.hot-update.js": "/js/app.a992ed7b22bd9b87b6db.hot-update.js",
    "/js/app.8c4baaf7339edd48bc45.hot-update.js": "/js/app.8c4baaf7339edd48bc45.hot-update.js",
    "/js/app.d8a7dc3f2d027eb3e45b.hot-update.js": "/js/app.d8a7dc3f2d027eb3e45b.hot-update.js",
    "/js/app.60eed7681c79e3262704.hot-update.js": "/js/app.60eed7681c79e3262704.hot-update.js",
    "/js/app.25feca278f5ccb9b5762.hot-update.js": "/js/app.25feca278f5ccb9b5762.hot-update.js",
    "/js/app.3a5252dbcbd371e00ca2.hot-update.js": "/js/app.3a5252dbcbd371e00ca2.hot-update.js",
    "/js/app.4e3a08ba914365e78068.hot-update.js": "/js/app.4e3a08ba914365e78068.hot-update.js",
    "/js/app.ab46865b97ca32451aac.hot-update.js": "/js/app.ab46865b97ca32451aac.hot-update.js",
    "/js/app.218282571ed70e1fe2f1.hot-update.js": "/js/app.218282571ed70e1fe2f1.hot-update.js",
    "/js/app.dc773a9fad9ab2943dc3.hot-update.js": "/js/app.dc773a9fad9ab2943dc3.hot-update.js",
    "/js/app.33387399560e76a2fb07.hot-update.js": "/js/app.33387399560e76a2fb07.hot-update.js",
    "/js/app.00cae8121aad71ea6316.hot-update.js": "/js/app.00cae8121aad71ea6316.hot-update.js",
    "/js/app.b0f76ebe741eec260730.hot-update.js": "/js/app.b0f76ebe741eec260730.hot-update.js",
    "/js/app.adf9fda79f1c51b76bc1.hot-update.js": "/js/app.adf9fda79f1c51b76bc1.hot-update.js",
    "/js/app.af3250c1c1656dbbee10.hot-update.js": "/js/app.af3250c1c1656dbbee10.hot-update.js",
    "/js/app.730627e17df7080d4b45.hot-update.js": "/js/app.730627e17df7080d4b45.hot-update.js",
    "/js/app.26842930b0babf9df45b.hot-update.js": "/js/app.26842930b0babf9df45b.hot-update.js",
    "/js/app.c254d02cbc571ef93b3e.hot-update.js": "/js/app.c254d02cbc571ef93b3e.hot-update.js",
    "/js/app.bd64f92b4323cb512c08.hot-update.js": "/js/app.bd64f92b4323cb512c08.hot-update.js",
    "/js/app.2561f3451936553f777b.hot-update.js": "/js/app.2561f3451936553f777b.hot-update.js",
    "/js/app.002c438c5ed5917b55f5.hot-update.js": "/js/app.002c438c5ed5917b55f5.hot-update.js",
    "/js/app.420ccf73d2796aee5428.hot-update.js": "/js/app.420ccf73d2796aee5428.hot-update.js",
    "/js/app.9780a1fa010c000996e4.hot-update.js": "/js/app.9780a1fa010c000996e4.hot-update.js",
    "/js/app.68ea3e4bfc0333274919.hot-update.js": "/js/app.68ea3e4bfc0333274919.hot-update.js",
    "/js/app.c3d81212e740ffe15876.hot-update.js": "/js/app.c3d81212e740ffe15876.hot-update.js",
    "/js/app.1f8bb5f543b49fa0aab7.hot-update.js": "/js/app.1f8bb5f543b49fa0aab7.hot-update.js",
    "/js/app.8ed99235d85c109281ba.hot-update.js": "/js/app.8ed99235d85c109281ba.hot-update.js",
    "/js/app.d33a878a9a751068b4df.hot-update.js": "/js/app.d33a878a9a751068b4df.hot-update.js",
    "/js/app.6799d2d2fff34c8d1266.hot-update.js": "/js/app.6799d2d2fff34c8d1266.hot-update.js",
    "/js/app.132ea93ccc50bddafc3a.hot-update.js": "/js/app.132ea93ccc50bddafc3a.hot-update.js",
    "/js/app.2978ff3ee4929f72ce84.hot-update.js": "/js/app.2978ff3ee4929f72ce84.hot-update.js",
    "/js/app.ac48b7d99e72c0828c6f.hot-update.js": "/js/app.ac48b7d99e72c0828c6f.hot-update.js",
    "/js/app.098a63e60de3476d5d72.hot-update.js": "/js/app.098a63e60de3476d5d72.hot-update.js",
    "/js/app.6f7da0e896bd9ec5c1d9.hot-update.js": "/js/app.6f7da0e896bd9ec5c1d9.hot-update.js",
    "/js/app.41acf09a23bb0efcf8ab.hot-update.js": "/js/app.41acf09a23bb0efcf8ab.hot-update.js",
    "/js/app.4b03a9655676693efa2d.hot-update.js": "/js/app.4b03a9655676693efa2d.hot-update.js",
    "/js/app.0799f9dde390f04f68e1.hot-update.js": "/js/app.0799f9dde390f04f68e1.hot-update.js",
    "/js/app.8fa1a92496cd5c13b4d3.hot-update.js": "/js/app.8fa1a92496cd5c13b4d3.hot-update.js",
    "/js/app.b68d72e725d0e47cc358.hot-update.js": "/js/app.b68d72e725d0e47cc358.hot-update.js",
    "/js/app.65c298ac824eceef4fb3.hot-update.js": "/js/app.65c298ac824eceef4fb3.hot-update.js",
    "/js/app.b0d974427a1be466005c.hot-update.js": "/js/app.b0d974427a1be466005c.hot-update.js",
    "/js/app.dd16a0a7ec13e292fd6a.hot-update.js": "/js/app.dd16a0a7ec13e292fd6a.hot-update.js",
    "/js/app.038846f668297ded057b.hot-update.js": "/js/app.038846f668297ded057b.hot-update.js",
    "/js/app.ad4a2d3a6b02de735e94.hot-update.js": "/js/app.ad4a2d3a6b02de735e94.hot-update.js",
    "/js/app.87a7d78d7edfd0b3f2d7.hot-update.js": "/js/app.87a7d78d7edfd0b3f2d7.hot-update.js",
    "/js/app.eb18b4c84a55c213b3db.hot-update.js": "/js/app.eb18b4c84a55c213b3db.hot-update.js",
    "/js/app.4b4779c2c4b925f6c47d.hot-update.js": "/js/app.4b4779c2c4b925f6c47d.hot-update.js",
    "/js/app.cd26550e4131be50fba6.hot-update.js": "/js/app.cd26550e4131be50fba6.hot-update.js",
    "/js/app.37a025171d19beb56cd7.hot-update.js": "/js/app.37a025171d19beb56cd7.hot-update.js",
    "/js/app.f4c067275263ee95ff64.hot-update.js": "/js/app.f4c067275263ee95ff64.hot-update.js",
    "/js/app.f49f6a5e2d3de05d5dcc.hot-update.js": "/js/app.f49f6a5e2d3de05d5dcc.hot-update.js",
    "/js/app.fd110b9f2edac9ea68c7.hot-update.js": "/js/app.fd110b9f2edac9ea68c7.hot-update.js",
    "/js/app.ff3ec65012e1547b124c.hot-update.js": "/js/app.ff3ec65012e1547b124c.hot-update.js",
    "/js/app.756c988557775a7e385f.hot-update.js": "/js/app.756c988557775a7e385f.hot-update.js",
    "/js/app.b77522416e43b7ea7222.hot-update.js": "/js/app.b77522416e43b7ea7222.hot-update.js",
    "/js/app.b6db5821f11eeedc59eb.hot-update.js": "/js/app.b6db5821f11eeedc59eb.hot-update.js",
    "/js/app.39d45e63e596cf52fdfe.hot-update.js": "/js/app.39d45e63e596cf52fdfe.hot-update.js",
    "/js/app.9f20b5d5381b9e23f48f.hot-update.js": "/js/app.9f20b5d5381b9e23f48f.hot-update.js",
    "/js/app.0a56da4db1a999cae310.hot-update.js": "/js/app.0a56da4db1a999cae310.hot-update.js",
    "/js/app.22583675831b527d768b.hot-update.js": "/js/app.22583675831b527d768b.hot-update.js",
    "/js/app.0545efee92d1e6de14cf.hot-update.js": "/js/app.0545efee92d1e6de14cf.hot-update.js",
    "/js/app.f3283021c6ccbb80f0f3.hot-update.js": "/js/app.f3283021c6ccbb80f0f3.hot-update.js",
    "/js/app.a79bd57b1dbff4429c1a.hot-update.js": "/js/app.a79bd57b1dbff4429c1a.hot-update.js",
    "/js/app.0a5c5fdebc2249e87fb1.hot-update.js": "/js/app.0a5c5fdebc2249e87fb1.hot-update.js",
    "/js/app.29b443046322f5a979ce.hot-update.js": "/js/app.29b443046322f5a979ce.hot-update.js",
    "/js/app.ecfab763caf581eca850.hot-update.js": "/js/app.ecfab763caf581eca850.hot-update.js",
    "/js/app.397ada0c190abaab1852.hot-update.js": "/js/app.397ada0c190abaab1852.hot-update.js",
    "/js/app.4ac956dc9d3a4d8e6d2b.hot-update.js": "/js/app.4ac956dc9d3a4d8e6d2b.hot-update.js",
    "/js/app.728a8a3ee78bbf5380f9.hot-update.js": "/js/app.728a8a3ee78bbf5380f9.hot-update.js",
    "/js/app.fb153d54173103ac7165.hot-update.js": "/js/app.fb153d54173103ac7165.hot-update.js",
    "/js/app.11f6e8082f210a41cff8.hot-update.js": "/js/app.11f6e8082f210a41cff8.hot-update.js",
    "/js/app.5e3ed9c7e5c80a676d7a.hot-update.js": "/js/app.5e3ed9c7e5c80a676d7a.hot-update.js",
    "/js/app.949c7bb440270c9e41ea.hot-update.js": "/js/app.949c7bb440270c9e41ea.hot-update.js",
    "/js/app.308bd645f8412c8637d8.hot-update.js": "/js/app.308bd645f8412c8637d8.hot-update.js",
    "/js/app.390831335430c346e9bf.hot-update.js": "/js/app.390831335430c346e9bf.hot-update.js",
    "/js/app.43612dbfbbe6b084dea3.hot-update.js": "/js/app.43612dbfbbe6b084dea3.hot-update.js",
    "/js/app.399b097973241e2455b0.hot-update.js": "/js/app.399b097973241e2455b0.hot-update.js",
    "/js/app.c784f79bc96983caf879.hot-update.js": "/js/app.c784f79bc96983caf879.hot-update.js",
    "/js/app.eadeb2ccc173113a6dab.hot-update.js": "/js/app.eadeb2ccc173113a6dab.hot-update.js",
    "/js/app.33df33bf43561f1610fb.hot-update.js": "/js/app.33df33bf43561f1610fb.hot-update.js",
    "/js/app.8de3851c884bdbbc7dc0.hot-update.js": "/js/app.8de3851c884bdbbc7dc0.hot-update.js",
    "/js/app.7fe5b5ea12b37c99b14d.hot-update.js": "/js/app.7fe5b5ea12b37c99b14d.hot-update.js",
    "/js/app.4d1d56d0f20a98b711c8.hot-update.js": "/js/app.4d1d56d0f20a98b711c8.hot-update.js",
    "/js/app.9b42c3980855c3d87e73.hot-update.js": "/js/app.9b42c3980855c3d87e73.hot-update.js",
    "/js/app.981d62270064979aecca.hot-update.js": "/js/app.981d62270064979aecca.hot-update.js",
    "/js/app.7f82dae8feb93ccc3094.hot-update.js": "/js/app.7f82dae8feb93ccc3094.hot-update.js",
    "/js/app.9e717d529000cbdcf390.hot-update.js": "/js/app.9e717d529000cbdcf390.hot-update.js",
    "/js/app.ab5f02c8d76c91329ce6.hot-update.js": "/js/app.ab5f02c8d76c91329ce6.hot-update.js",
    "/js/app.e1ea958c2d87e4695237.hot-update.js": "/js/app.e1ea958c2d87e4695237.hot-update.js",
    "/js/app.5175186d1fae0ca3bd93.hot-update.js": "/js/app.5175186d1fae0ca3bd93.hot-update.js",
    "/js/app.20cc9cff63afa4d2fa9e.hot-update.js": "/js/app.20cc9cff63afa4d2fa9e.hot-update.js",
    "/js/app.6dfb8d9028707945a7ff.hot-update.js": "/js/app.6dfb8d9028707945a7ff.hot-update.js",
    "/js/app.9d21526d229df50c742b.hot-update.js": "/js/app.9d21526d229df50c742b.hot-update.js",
    "/js/app.d0a92c28a46ccbbc6bac.hot-update.js": "/js/app.d0a92c28a46ccbbc6bac.hot-update.js",
    "/js/app.c6f2ca6f86f66e4f75c5.hot-update.js": "/js/app.c6f2ca6f86f66e4f75c5.hot-update.js",
    "/js/app.2793492279641bcc5095.hot-update.js": "/js/app.2793492279641bcc5095.hot-update.js",
    "/js/app.077a4bd27d07d65fcbef.hot-update.js": "/js/app.077a4bd27d07d65fcbef.hot-update.js",
    "/js/app.2420850a3c4e3d74c16d.hot-update.js": "/js/app.2420850a3c4e3d74c16d.hot-update.js"
}
